{"stem":"198","instances":[{"docId":"A198","docUri":"A198.html","score":2,"contexts":[{"form":"198","weight":"1","pos":18,"context":"A<mark>198<\/mark>.","fid":"d201e48"},{"form":"198","weight":"1","pos":64,"context":"Druck: Familienkorrespondenz Bd. 1, Nr. <mark>198<\/mark>, S. 386-387.","fid":"d201e68"}]},{"docId":"A194","docUri":"A194.html","score":2,"contexts":[{"form":"198","weight":"1","pos":23,"context":"Vgl. Nr. A<mark>198<\/mark>.","fid":"d197e56"},{"form":"198","weight":"1","pos":25,"context":"See no. A<mark>198<\/mark>.","fid":"d197e59"}]},{"docId":"toc","docUri":"toc.html","score":1,"contexts":[{"form":"198","weight":"1","pos":1174,"context":"A<mark>198<\/mark>.xml","fid":"tocTable"}]},{"docId":"A023","docUri":"A023.html","score":1,"contexts":[{"form":"198","weight":"1","pos":207,"context":"..., Jahrbücher der Literatur 111, S. 196—<mark>198<\/mark>. — Auszug in DRA 3, S. 834 f.,...","fid":"d27e69"}]},{"docId":"A021","docUri":"A021.html","score":1,"contexts":[{"form":"198","weight":"1","pos":2696,"context":"...Im übrigen vgl. Bauer, S. 192, <mark>198<\/mark>.","fid":"d25e588"}]},{"docId":"A035","docUri":"A035.html","score":1,"contexts":[{"form":"198","weight":"1","pos":970,"context":"..., S. 114 ff. Vgl. Bauer, S. <mark>198<\/mark> f.","fid":"d39e212"}]},{"docId":"A220","docUri":"A220.html","score":1,"contexts":[{"form":"198","weight":"1","pos":915,"context":"Gemeint ist Nr. A<mark>198<\/mark>.","fid":"d223e433"}]}]}