{"stem":"amstetten","instances":[{"docId":"listplace","docUri":"listplace.html","score":2,"contexts":[{"form":"Amstetten","weight":"1","pos":4904,"context":"<mark>Amstetten<\/mark>","fid":"tocTable"},{"form":"Amstetten","weight":"1","pos":4909,"context":"Ferdinand an Margareta, 1524 November 13, <mark>Amstetten<\/mark>.","fid":"tocTable"}]},{"docId":"A109","docUri":"A109.html","score":3,"contexts":[{"form":"Amstetten","weight":"2","pos":16,"context":"Ferdinand an Margareta, 1524 November 13, <mark>Amstetten<\/mark>.","fid":"page"},{"form":"Amstetten","weight":"1","pos":23,"context":"1524 November 13. <mark>Amstetten<\/mark>.","fid":"d113e47"}]},{"docId":"listperson","docUri":"listperson.html","score":2,"contexts":[{"form":"Amstetten","weight":"1","pos":3736,"context":"Ferdinand an Margareta, 1524 November 13, <mark>Amstetten<\/mark>.","fid":"tocTable"},{"form":"Amstetten","weight":"1","pos":11086,"context":"Ferdinand an Margareta, 1524 November 13, <mark>Amstetten<\/mark>.","fid":"tocTable"}]},{"docId":"toc","docUri":"toc.html","score":1,"contexts":[{"form":"Amstetten","weight":"1","pos":1523,"context":"Ferdinand an Margareta, 1524 November 13, <mark>Amstetten<\/mark>.","fid":"tocTable"}]}]}