{"stem":"approbatum","instances":[{"docId":"A175","docUri":"A175.html","score":2,"contexts":[{"form":"approbatum","weight":"1","pos":993,"context":"..., tractatum, promissum, obligatum, confirmatum, <mark>approbatum<\/mark>, innovatum, assignatum, assecuratum, inscriptum,...","fid":"d178e185"},{"form":"approbatum","weight":"1","pos":1518,"context":"...superiori, nisi quod pro istis verbis confirmatum, <mark>approbatum<\/mark>, innovatum, assignatum, assecuratum, inscriptum ponantur...","fid":"d178e279"}]}]}