{"stem":"austrich","instances":[{"docId":"A232","docUri":"A232.html","score":2,"contexts":[{"form":"Austriche","weight":"1","pos":195,"context":"...me pries que jed) veullie aller au <mark>Austriche<\/mark> et vous monstrer tour de bon frere, m...","fid":"d235e75"},{"form":"Austriche","weight":"1","pos":238,"context":"...g) quatre jours m’en partir pour aler au <mark>Austriche<\/mark>, comme le me demandes, et ne me...","fid":"d235e75"}]},{"docId":"A016","docUri":"A016.html","score":1,"contexts":[{"form":"Austriche","weight":"1","pos":128,"context":"...cidevant proumeu, que l’evesque de Vyanne en <mark>Austriche<\/mark>, moderne, le print pour son coadjuteur à...","fid":"d20e74"}]}]}