{"stem":"besongn","instances":[{"docId":"A212","docUri":"A212.html","score":3,"contexts":[{"form":"besongner","weight":"1","pos":328,"context":"...qui valist, combien que j’ai fait entendre et <mark>besongner<\/mark> avec les marchans de pardeça pour pouoir recouvrer une...","fid":"d215e85"},{"form":"besongner","weight":"1","pos":385,"context":"...rebours et difficilles que n’ai espoir de riens savoir <mark>besongner<\/mark> avec eulx. Parquoi, mme, et...","fid":"d215e85"},{"form":"besongner","weight":"1","pos":472,"context":"...de si mauvaise sorte, il est temps de <mark>besongner<\/mark> ou jamais. Et sur ce, mme,...","fid":"d215e85"}]},{"docId":"A261","docUri":"A261.html","score":1,"contexts":[{"form":"besongner","weight":"1","pos":1061,"context":"..., sans argent riens ou bien peu se peult <mark>besongner<\/mark> avec eulx, parquoi me semble ferez bien y...","fid":"d264e300"}]},{"docId":"A032","docUri":"A032.html","score":1,"contexts":[{"form":"besongne","weight":"1","pos":354,"context":"...places. Je prie dieu qui leur doint bien <mark>besongne<\/mark>, car il me redundera au grant bien et...","fid":"d36e138"}]},{"docId":"A053","docUri":"A053.html","score":1,"contexts":[{"form":"besongner","weight":"1","pos":278,"context":"...suis monsr tousiours actendant le visconte Hannart pour <mark>besongner<\/mark> à ceste diete, où sans sa venue et...","fid":"d57e112"}]},{"docId":"A124","docUri":"A124.html","score":1,"contexts":[{"form":"besongne","weight":"1","pos":193,"context":"...du 16e de decembre ensemble la copie du <mark>besongne<\/mark> de l’archevesque de Capua dont, monsr,...","fid":"d127e73"}]}]}