{"stem":"conferr","instances":[{"docId":"A076","docUri":"A076.html","score":1,"contexts":[{"form":"conferre","weight":"1","pos":2034,"context":"...Sua nobis indulserat, sine assensu regiminis propria auctoritate <mark>conferre<\/mark> prẹstareque liceat, quo in numero sint etiam illẹ...","fid":"d80e167"}]},{"docId":"A065","docUri":"A065.html","score":1,"contexts":[{"form":"conferre","weight":"1","pos":2728,"context":"...ante suffragia cumq5) cẹteris sui ordinis quidquam <mark>conferre<\/mark> vel consultare.","fid":"d69e918"}]}]}