{"stem":"consuir","instances":[{"docId":"A167","docUri":"A167.html","score":1,"contexts":[{"form":"consuir","weight":"1","pos":358,"context":"..., affin que au plaisir de dieu il puist <mark>consuir<\/mark> generacion. Etd) combien que desia en...","fid":"d170e177"}]},{"docId":"A149","docUri":"A149.html","score":1,"contexts":[{"form":"consuir","weight":"1","pos":560,"context":"...affin que tant plustost à l’aide de dieu puissez <mark>consuir<\/mark> generation qu’est le fruict de mariaige.","fid":"d152e162"}]}]}