{"stem":"direz","instances":[{"docId":"A046","docUri":"A046.html","score":3,"contexts":[{"form":"direz","weight":"1","pos":916,"context":"...Maistre Jehan Hannart, visconte de Lombeke, vouz <mark>direz<\/mark> à part à mme, nostre bonne tante,...","fid":"d50e207"},{"form":"direz","weight":"1","pos":1028,"context":"...dit le serviteur dud. Beaurain. Vous lui <mark>direz<\/mark> aussi les apprestes de nostre armée telle que sçavez...","fid":"d50e207"},{"form":"direz","weight":"1","pos":1042,"context":"...sçavez et la dilligence que nous faisons et lui <mark>direz<\/mark> que desirons fort qu’elle tienne main vers le roi...","fid":"d50e207"}]}]}