{"stem":"diroi","instances":[{"docId":"A066","docUri":"A066.html","score":2,"contexts":[{"form":"diroie","weight":"1","pos":407,"context":"...evesque de Treves.d) Et quant je <mark>diroie<\/mark> tout le contenu en icelles, par aventure ne...","fid":"d70e82"},{"form":"diroie","weight":"1","pos":413,"context":"...tout le contenu en icelles, par aventure ne <mark>diroie<\/mark> je hors de la verité, pourquoi en parlant...","fid":"d70e82"}]},{"docId":"A187","docUri":"A187.html","score":1,"contexts":[{"form":"diroie","weight":"1","pos":736,"context":".... don Pedro pour, selon ce que lui <mark>diroie<\/mark>, declairer ausd. deputéz de vostre part,...","fid":"d190e269"}]}]}