{"stem":"doient","instances":[{"docId":"A216","docUri":"A216.html","score":2,"contexts":[{"form":"doient","weight":"1","pos":3392,"context":"...cause au contraire, pourquoi faire le puissent ou <mark>doient<\/mark> qu’ilz tiennent tout en surceance et mon advertissement et...","fid":"d219e464"},{"form":"doient","weight":"1","pos":4441,"context":"...Lutheriens, qu’est chose bien reprouvée que telles gens <mark>doient<\/mark> regir et gouverner l’empire et vous prie y bien...","fid":"d219e725"}]}]}