{"stem":"faith","instances":[{"docId":"A158","docUri":"A158.html","score":1,"contexts":[{"form":"faith","weight":"1","pos":175,"context":"...the Imperial Diet until St. Martin's Day. Catholic <mark>faith<\/mark>. 10. Impending marriage to the Infanta of Portugal...","fid":"d161e63"}]},{"docId":"A063","docUri":"A063.html","score":1,"contexts":[{"form":"faith","weight":"1","pos":442,"context":".... But since the Pope seems to give some <mark>faith<\/mark> to these unexpected messages and has asked F to...","fid":"d67e120"}]},{"docId":"A076","docUri":"A076.html","score":1,"contexts":[{"form":"faith","weight":"1","pos":697,"context":".... Lutheran beliefs. 19. Various religious articles of <mark>faith<\/mark>, which deny Christ's divinity etc., are spreading...","fid":"d80e63"}]}]}