{"stem":"felicissim","instances":[{"docId":"A202","docUri":"A202.html","score":1,"contexts":[{"form":"felicissime","weight":"1","pos":451,"context":"...re eciam Serti grates amplissimas agimus et eandem <mark>felicissime<\/mark> valere optamus.","fid":"d205e146"}]},{"docId":"A200","docUri":"A200.html","score":1,"contexts":[{"form":"felicissime","weight":"1","pos":186,"context":"...boni consequutum fore intellexerimus. Sertem Vram <mark>felicissime<\/mark> valere optamus.","fid":"d203e71"}]},{"docId":"A210","docUri":"A210.html","score":1,"contexts":[{"form":"felicissime","weight":"1","pos":321,"context":"...in maiori nunquam fuerit. Vram Serttem <mark>felicissime<\/mark> valere optamus.","fid":"d213e126"}]},{"docId":"A101","docUri":"A101.html","score":1,"contexts":[{"form":"felicissime","weight":"1","pos":325,"context":"...cultus. Et valeat Vra Sertas quam <mark>felicissime<\/mark>.","fid":"d105e112"}]},{"docId":"A173","docUri":"A173.html","score":1,"contexts":[{"form":"felicissime","weight":"1","pos":302,"context":"...erit. Et valeat Vra Sertas quam <mark>felicissime<\/mark>. Datum . . .","fid":"d176e95"}]}]}