{"stem":"fuesen","instances":[{"docId":"A136","docUri":"A136.html","score":3,"contexts":[{"form":"fuesen","weight":"1","pos":680,"context":"...con el dicho conde y micer George, que <mark>fuesen<\/mark> á servir á Su Md, asi porque...","fid":"d139e125"},{"form":"fuesen","weight":"1","pos":859,"context":"...posibles al principio para los retener, que no <mark>fuesen<\/mark> en servicio de Franceses y despues para retirallos,...","fid":"d139e169"},{"form":"fuesen","weight":"1","pos":1060,"context":"...en particular, los quales como la mayor parte <mark>fuesen<\/mark> vasallos de Su A, con las promesas que les...","fid":"d139e216"}]},{"docId":"A261","docUri":"A261.html","score":1,"contexts":[{"form":"fuesen","weight":"1","pos":1346,"context":"...caros, deciendoles cómo S. M. les ayudaria que <mark>fuesen<\/mark> pagados de lo que el rey de Francia les...","fid":"d264e462"}]},{"docId":"A216","docUri":"A216.html","score":1,"contexts":[{"form":"fuesen","weight":"1","pos":4533,"context":"...poder castigar á todos los que hiziesen porqué y <mark>fuesen<\/mark> deservidores. Lo otro que venia á dar cuenta...","fid":"d219e748"}]}]}