{"stem":"glapion","instances":[{"docId":"A076","docUri":"A076.html","score":1,"contexts":[{"form":"Glapion","weight":"1","pos":14969,"context":"...Auslegungen erfuhren. Seit dem Tode des kaiserlichen Beichtvaters <mark>Glapion<\/mark> fehlte der wichtigste Zeuge. Schon in der Instruktion...","fid":"d80e2633"}]},{"docId":"listperson","docUri":"listperson.html","score":1,"contexts":[{"form":"Glapion","weight":"1","pos":8953,"context":"<mark>Glapion<\/mark>, Jean, Beichtvater Ks","fid":"tocTable"}]},{"docId":"A021","docUri":"A021.html","score":1,"contexts":[{"form":"Glapion","weight":"1","pos":2687,"context":"K’s Beichtvater, Juan <mark>Glapion<\/mark>, starb am 14. September 1522. Villa,...","fid":"d25e588"}]}]}