{"stem":"granad","instances":[{"docId":"A252","docUri":"A252.html","score":2,"contexts":[{"form":"Granade","weight":"1","pos":1905,"context":"Escriptk) en <mark>Granade<\/mark>, le 23e de novembre an 26.","fid":"d255e305"},{"form":"Granade","weight":"1","pos":2103,"context":"...Hand hinzugefügt. - k) in W1 De <mark>Granade<\/mark>, ce dernier jour de novembre, ähnlich B....","fid":"d255e393"}]},{"docId":"A231","docUri":"A231.html","score":2,"contexts":[{"form":"Granade","weight":"1","pos":335,"context":"...copie des lettres que l’empereur lui avoit escript de <mark>Granade<\/mark> du 16 de juillet de son intencion sur ce...","fid":"d234e143"},{"form":"Granade","weight":"1","pos":843,"context":"...soit parti. Led. seigneur estoit parti de <mark>Granade<\/mark> et tiroit vers Valladolid pour y tenir les cortes...","fid":"d234e398"}]},{"docId":"A257","docUri":"A257.html","score":1,"contexts":[{"form":"Granade","weight":"1","pos":156,"context":"De <mark>Granade<\/mark>, le dernier jour de nouvembre ao 26....","fid":"d260e87"}]},{"docId":"A256","docUri":"A256.html","score":1,"contexts":[{"form":"Granade","weight":"1","pos":780,"context":"Escript en <mark>Granade<\/mark>, le 29e de novembre ao 26....","fid":"d259e181"}]}]}