{"stem":"habuerint","instances":[{"docId":"A065","docUri":"A065.html","score":3,"contexts":[{"form":"habuerint","weight":"1","pos":2176,"context":"...cum illis et apud illos locum pariter et vocem <mark>habuerint<\/mark>, item in Wormaciensi ordinatione cautum esse, ut...","fid":"d69e786"},{"form":"habuerint","weight":"1","pos":2192,"context":"...civitatum intersint regimini imperiali, qui illic voces suas <mark>habuerint<\/mark> et adhuc habent, preterea quod ultra, quam...","fid":"d69e786"},{"form":"habuerint","weight":"1","pos":2491,"context":"Quod autem interdum sessionem non <mark>habuerint<\/mark>, id ideo evenisse, quod civitates inter se...","fid":"d69e885"}]}]}