{"stem":"haze","instances":[{"docId":"A136","docUri":"A136.html","score":4,"contexts":[{"form":"haze","weight":"1","pos":529,"context":"...de otra tan grande y que muy mayor la <mark>haze<\/mark> haberla Su Md conseguido sin ayuda ni favor...","fid":"d139e76"},{"form":"haze","weight":"1","pos":2382,"context":"...costa que asta aquí Su A ha echo y <mark>haze<\/mark>, asi en la guerra de Ytalia, y...","fid":"d139e488"},{"form":"haze","weight":"1","pos":2536,"context":"...pero el deseo que á su servicio tiene le <mark>haze<\/mark> dezir, que se acuerde de las alteraciones de...","fid":"d139e528"},{"form":"haze","weight":"1","pos":2596,"context":"...que no dispornia del, lo qual Su A <mark>haze<\/mark> saber al enperador, no para otro efeto,...","fid":"d139e536"}]},{"docId":"A008","docUri":"A008.html","score":1,"contexts":[{"form":"haze","weight":"1","pos":555,"context":"...tengays por bueno esto y creyais que todo se <mark>haze<\/mark> por vuestro bien, y vos acordeys siempre del...","fid":"d12e102"}]},{"docId":"A140","docUri":"A140.html","score":1,"contexts":[{"form":"haze","weight":"1","pos":550,"context":"Iten como Su A ha echo y <mark>haze<\/mark> todas las provisiones posibles asi en dar á la...","fid":"d143e124"}]}]}