{"stem":"herzogthum","instances":[{"docId":"A036","docUri":"A036.html","score":1,"contexts":[{"form":"Herzogthums","weight":"1","pos":2189,"context":"...Mömpelgard. Chr. Fr. Sattler, Geschichte des <mark>Herzogthums<\/mark> Würtenberg 2, S. 100 f.","fid":"d40e523"}]},{"docId":"A162","docUri":"A162.html","score":1,"contexts":[{"form":"Herzogthums","weight":"1","pos":335,"context":"...Ordnung auferlegt worden sind. Sattler, Gesch. des <mark>Herzogthums<\/mark> Würtenberg unter der Regierung der Herzogen 3., Beilagen,...","fid":"d165e145"}]}]}