{"stem":"ingratam","instances":[{"docId":"A076","docUri":"A076.html","score":2,"contexts":[{"form":"ingratam","weight":"1","pos":10874,"context":"..., ipsam restitutionem exequi permisimus, utcunque intollerabilem et <mark>ingratam<\/mark> provincialibus nostris, quos ad hoc, quibus potuimus...","fid":"d80e1756"},{"form":"ingratam","weight":"1","pos":11712,"context":"...possemus, quoniam sciremus eam esse Mti Suẹ <mark>ingratam<\/mark> et solam sufficere, quod felix ille cursus rerum...","fid":"d80e1940"}]}]}