{"stem":"joachin","instances":[{"docId":"A050","docUri":"A050.html","score":2,"contexts":[{"form":"Joachin","weight":"1","pos":1732,"context":"...chevaulx et les mena jusques aux pais du marquis <mark>Joachin<\/mark>, electeur. Et la venuz, il n’eust...","fid":"d54e302"},{"form":"Joachin","weight":"1","pos":1784,"context":"..., la roine est emprès le susd. marquis <mark>Joachin<\/mark>, electeur, tous deux vivans non comme roix...","fid":"d54e302"}]},{"docId":"A136","docUri":"A136.html","score":1,"contexts":[{"form":"Joachin","weight":"1","pos":1139,"context":"...el dicho rey de Francia praticaba con el marqués <mark>Joachin<\/mark>, elector de Brandanburc, asi para que el...","fid":"d139e245"}]},{"docId":"A085","docUri":"A085.html","score":1,"contexts":[{"form":"Joachin","weight":"1","pos":387,"context":"...envoyer leurs ambassadeurs les duc de Saxen, marquis <mark>Joachin<\/mark> de Brandeburg et conte Palatin, electeurs, pour...","fid":"d89e132"}]}]}