{"stem":"justement","instances":[{"docId":"A216","docUri":"A216.html","score":1,"contexts":[{"form":"justement","weight":"1","pos":1742,"context":"..., et ne pourroit sa Ste se douloir <mark>justement<\/mark> ni dire que par tel edict et remission de...","fid":"d219e201"}]},{"docId":"A066","docUri":"A066.html","score":1,"contexts":[{"form":"justement","weight":"1","pos":727,"context":"...moderé et honneste.k) Lesquelles fastides plus <mark>justement<\/mark> eusse devoré icelles, si de ce fust venu...","fid":"d70e82"}]}]}