{"stem":"l'euss","instances":[{"docId":"A047","docUri":"A047.html","score":1,"contexts":[{"form":"l’eusse","weight":"1","pos":410,"context":"...c1) trater avecques lesd. Veneciens, je <mark>l’eusse<\/mark> conduictd1) le traté avecques eulx plus à...","fid":"d51e181"}]},{"docId":"A167","docUri":"A167.html","score":1,"contexts":[{"form":"l’eusse","weight":"1","pos":138,"context":"...France dont, mme, combien que desia <mark>l’eusse<\/mark> entendu, vous mercie bien humblement, et me...","fid":"d170e76"}]},{"docId":"A050","docUri":"A050.html","score":1,"contexts":[{"form":"l’eusse","weight":"1","pos":2085,"context":"...les bagues à telz pris que à grant paine <mark>l’eusse<\/mark> peu payer de toutes celles que rapportai de pardela...","fid":"d54e365"}]},{"docId":"A244","docUri":"A244.html","score":1,"contexts":[{"form":"l’eusse","weight":"1","pos":159,"context":"..., par vous requise, ou autre que je <mark>l’eusse<\/mark> fait et ancoires feroie,b) et feisant...","fid":"d247e77"}]},{"docId":"A070","docUri":"A070.html","score":1,"contexts":[{"form":"l’eusse","weight":"1","pos":265,"context":"...voulentiers ne vouldrions. Quoi non obstant que je <mark>l’eusse<\/mark> dit ausd. princes feablement et appart, si...","fid":"d74e71"}]},{"docId":"A053","docUri":"A053.html","score":1,"contexts":[{"form":"l’eusse","weight":"1","pos":186,"context":"...) que, s’ilz ne sont depeschéz ainsi que <mark>l’eusse<\/mark> bien desiré, que ce a esté la cause...","fid":"d57e93"}]}]}