{"stem":"landsknechtführ","instances":[{"docId":"A046","docUri":"A046.html","score":1,"contexts":[{"form":"Landsknechtführer","weight":"1","pos":108,"context":"...Count Felix of Werdenberg as a mercenary captain (<mark>Landsknechtführer<\/mark>). 3. Beaurain's negotiations with the Duke of Bourbon...","fid":"d50e63"}]},{"docId":"listperson","docUri":"listperson.html","score":1,"contexts":[{"form":"Landsknechtführer","weight":"1","pos":10004,"context":"Werdenberg, Felix, Graf von, <mark>Landsknechtführer<\/mark>","fid":"tocTable"}]}]}