{"stem":"ludwig","instances":[{"docId":"listperson","docUri":"listperson.html","score":62,"contexts":[{"form":"Ludwig","weight":"1","pos":419,"context":"<mark>Ludwig<\/mark> II. an Ferdinand, 1526 Juni 6, Ofen....","fid":"tocTable"},{"form":"Ludwig","weight":"1","pos":548,"context":"Ferdinand an <mark>Ludwig<\/mark> II., 1524 April 16, Nürnberg.","fid":"tocTable"},{"form":"Ludwig","weight":"1","pos":768,"context":"<mark>Ludwig<\/mark> II. an Ferdinand, 1526 Juni 6, Ofen....","fid":"tocTable"},{"form":"Ludwig","weight":"1","pos":813,"context":"<mark>Ludwig<\/mark> II. an Ferdinand, 1526 Juli 15, Ofen....","fid":"tocTable"},{"form":"Ludwig","weight":"1","pos":846,"context":"<mark>Ludwig<\/mark> II. an Ferdinand, 1523 April 24, Neutra....","fid":"tocTable"},{"form":"Ludwig","weight":"1","pos":851,"context":"<mark>Ludwig<\/mark> II. an Ferdinand, 1523 April 24, Neutra....","fid":"tocTable"},{"form":"Ludwig","weight":"1","pos":887,"context":"Ferdinand an <mark>Ludwig<\/mark> II., 1524 April 16, Nürnberg.","fid":"tocTable"},{"form":"Ludwig","weight":"1","pos":1807,"context":"Ferdinand an <mark>Ludwig<\/mark> II., 1524 April 16, Nürnberg.","fid":"tocTable"},{"form":"Ludwig","weight":"1","pos":2678,"context":"<mark>Ludwig<\/mark> II., König von Böhmen und Ungarn","fid":"tocTable"},{"form":"Ludwig","weight":"1","pos":2756,"context":"<mark>Ludwig<\/mark> II. an Ferdinand, 1526 Mai 29, Ofen....","fid":"tocTable"},{"form":"Ludwig","weight":"1","pos":2766,"context":"<mark>Ludwig<\/mark> II. an Ferdinand, 1522 Dezember 10, Prag....","fid":"tocTable"},{"form":"Ludwig","weight":"1","pos":2829,"context":"<mark>Ludwig<\/mark> II. an Ferdinand, 1523 Juni 20, Ofen....","fid":"tocTable"},{"form":"Ludwig","weight":"1","pos":2839,"context":"<mark>Ludwig<\/mark> II. an Ferdinand, 1526 Juni 6, Ofen....","fid":"tocTable"},{"form":"Ludwig","weight":"1","pos":2844,"context":"<mark>Ludwig<\/mark> an Ferdinand, 1525 August 24, Ofen.","fid":"tocTable"},{"form":"Ludwig","weight":"1","pos":2850,"context":"Ferdinand an <mark>Ludwig<\/mark> II., 1525 Oktober 1, Tübingen.","fid":"tocTable"},{"form":"Ludwig","weight":"1","pos":2935,"context":"<mark>Ludwig<\/mark> II. an Ferdinand, 1526 Februar 22, Ofen....","fid":"tocTable"},{"form":"Ludwig","weight":"1","pos":2941,"context":"Ferdinand an Kg <mark>Ludwig<\/mark> II., 1523 Dezember 6, Nürnberg.","fid":"tocTable"},{"form":"Ludwig","weight":"1","pos":2981,"context":"Ferdinand an <mark>Ludwig<\/mark> II., 1524 Februar 18, Nürnberg.","fid":"tocTable"},{"form":"Ludwig","weight":"1","pos":5009,"context":"Ferdinand an <mark>Ludwig<\/mark> II., 1524 April 16, Nürnberg.","fid":"tocTable"},{"form":"Ludwig","weight":"1","pos":5130,"context":"<mark>Ludwig<\/mark> II. an Ferdinand, 1522 Dezember 10, Prag....","fid":"tocTable"},{"form":"Ludwig","weight":"1","pos":5704,"context":"<mark>Ludwig<\/mark> X., Herzog von Bayern (Landshut)","fid":"tocTable"},{"form":"Ludwig","weight":"1","pos":6326,"context":"<mark>Ludwig<\/mark> II. an Ferdinand, 1523 Juni 20, Ofen....","fid":"tocTable"},{"form":"Ludwig","weight":"1","pos":6707,"context":"<mark>Ludwig<\/mark> V. von der Pfalz, Kurfürst","fid":"tocTable"},{"form":"Ludwig","weight":"1","pos":6947,"context":"<mark>Ludwig<\/mark> II. an Ferdinand, 1522 Dezember 10, Prag....","fid":"tocTable"},{"form":"Ludwig","weight":"1","pos":8100,"context":"Ferdinand an <mark>Ludwig<\/mark>, 1526 März 26, Tübingen.","fid":"tocTable"},{"form":"Ludwig","weight":"1","pos":8301,"context":"<mark>Ludwig<\/mark> II. an Ferdinand, 1523 April 24, Neutra....","fid":"tocTable"},{"form":"Ludwig","weight":"1","pos":9398,"context":"<mark>Ludwig<\/mark> II. an Ferdinand, 1526 Mai 29, Ofen....","fid":"tocTable"},{"form":"Ludwig","weight":"1","pos":9412,"context":"<mark>Ludwig<\/mark> II. an Ferdinand, 1526 Mai 29, Ofen....","fid":"tocTable"},{"form":"Ludwig","weight":"1","pos":9422,"context":"<mark>Ludwig<\/mark> II. an Ferdinand, 1526 Juni 6, Ofen....","fid":"tocTable"},{"form":"Ludwig","weight":"1","pos":9444,"context":"Ferdinand an <mark>Ludwig<\/mark> II., 1525 Oktober 1, Tübingen.","fid":"tocTable"},{"form":"Ludwig","weight":"1","pos":9569,"context":"<mark>Ludwig<\/mark> II. an Ferdinand, 1522 Dezember 10, Prag....","fid":"tocTable"},{"form":"Ludwig","weight":"1","pos":9576,"context":"<mark>Ludwig<\/mark> II. an Ferdinand, 1522 Dezember 10, Prag....","fid":"tocTable"},{"form":"Ludwig","weight":"1","pos":9583,"context":"<mark>Ludwig<\/mark> II. an Ferdinand, 1522 Dezember 10, Prag....","fid":"tocTable"},{"form":"Ludwig","weight":"1","pos":9590,"context":"<mark>Ludwig<\/mark> II. an Ferdinand, 1522 Dezember 10, Prag....","fid":"tocTable"},{"form":"Ludwig","weight":"1","pos":9597,"context":"<mark>Ludwig<\/mark> II. an Ferdinand, 1522 Dezember 10, Prag....","fid":"tocTable"},{"form":"Ludwig","weight":"1","pos":9604,"context":"<mark>Ludwig<\/mark> II. an Ferdinand, 1522 Dezember 10, Prag....","fid":"tocTable"},{"form":"Ludwigs","weight":"1","pos":9769,"context":"...Bischof von Gurk, Diplomat (u. a. im Dienst <mark>Ludwigs<\/mark> II. von Ungarn)","fid":"tocTable"},{"form":"Ludwig","weight":"1","pos":11298,"context":"<mark>Ludwig<\/mark> II. an Ferdinand, 1523 April 24, Neutra....","fid":"tocTable"},{"form":"Ludwig","weight":"1","pos":11356,"context":"<mark>Ludwig<\/mark> II. an Ferdinand, 1523 Juni 20, Ofen....","fid":"tocTable"},{"form":"Ludwig","weight":"1","pos":11468,"context":"<mark>Ludwig<\/mark> II. an Ferdinand, 1526 Juni 6, Ofen....","fid":"tocTable"},{"form":"Ludwig","weight":"1","pos":11507,"context":"Ferdinand an <mark>Ludwig<\/mark> II., 1525 Oktober 1, Tübingen.","fid":"tocTable"},{"form":"Ludwig","weight":"1","pos":11516,"context":"Ferdinand an <mark>Ludwig<\/mark> II., 1525 Oktober 1, Tübingen.","fid":"tocTable"},{"form":"Ludwig","weight":"1","pos":11523,"context":"Ferdinand an <mark>Ludwig<\/mark> II., 1525 Oktober 1, Tübingen.","fid":"tocTable"},{"form":"Ludwig","weight":"1","pos":11530,"context":"Ferdinand an <mark>Ludwig<\/mark> II., 1525 Oktober 1, Tübingen.","fid":"tocTable"},{"form":"Ludwig","weight":"1","pos":11537,"context":"Ferdinand an <mark>Ludwig<\/mark> II., 1525 Oktober 1, Tübingen.","fid":"tocTable"},{"form":"Ludwig","weight":"1","pos":11543,"context":"Ferdinand an <mark>Ludwig<\/mark> II., 1525 Oktober 1, Tübingen.","fid":"tocTable"},{"form":"Ludwig","weight":"1","pos":11550,"context":"Ferdinand an <mark>Ludwig<\/mark> II., 1525 Oktober 1, Tübingen.","fid":"tocTable"},{"form":"Ludwig","weight":"1","pos":11557,"context":"Ferdinand an <mark>Ludwig<\/mark> II., 1525 Oktober 1, Tübingen.","fid":"tocTable"},{"form":"Ludwig","weight":"1","pos":11567,"context":"Ferdinand an <mark>Ludwig<\/mark> II., 1525 Oktober 1, Tübingen.","fid":"tocTable"},{"form":"Ludwig","weight":"1","pos":11718,"context":"Helfenstein, Graf <mark>Ludwig<\/mark> von","fid":"tocTable"},{"form":"Ludwig","weight":"1","pos":11773,"context":"Ferdinand an <mark>Ludwig<\/mark>, 1526 März 26, Tübingen.","fid":"tocTable"},{"form":"Ludwig","weight":"1","pos":11838,"context":"Ferdinand an Kg <mark>Ludwig<\/mark> II., 1523 Dezember 6, Nürnberg.","fid":"tocTable"},{"form":"Ludwig","weight":"1","pos":11843,"context":"Ferdinand an <mark>Ludwig<\/mark> II., 1524 April 16, Nürnberg.","fid":"tocTable"},{"form":"Ludwig","weight":"1","pos":11918,"context":"<mark>Ludwig<\/mark> II. an Ferdinand, 1523 April 24, Neutra....","fid":"tocTable"},{"form":"Ludwig","weight":"1","pos":11925,"context":"<mark>Ludwig<\/mark> II. an Ferdinand, 1523 April 24, Neutra....","fid":"tocTable"},{"form":"Ludwig","weight":"1","pos":11931,"context":"Ferdinand an Kg <mark>Ludwig<\/mark> II., 1523 Dezember 6, Nürnberg.","fid":"tocTable"},{"form":"Ludwig","weight":"1","pos":12047,"context":"Ferdinand an <mark>Ludwig<\/mark>, 1526 März 26, Tübingen.","fid":"tocTable"},{"form":"Ludwig","weight":"1","pos":12269,"context":"<mark>Ludwig<\/mark> II. an Ferdinand, 1526 Februar 22, Ofen....","fid":"tocTable"},{"form":"Ludwig","weight":"1","pos":12274,"context":"<mark>Ludwig<\/mark> II. an Ferdinand, 1526 Februar 22, Ofen....","fid":"tocTable"},{"form":"Ludwig","weight":"1","pos":12283,"context":"<mark>Ludwig<\/mark> II. an Ferdinand, 1526 Februar 22, Ofen....","fid":"tocTable"},{"form":"Ludwig","weight":"1","pos":12300,"context":"<mark>Ludwig<\/mark> II. an Ferdinand, 1526 Februar 22, Ofen....","fid":"tocTable"},{"form":"Ludwig","weight":"1","pos":12310,"context":"<mark>Ludwig<\/mark> II. an Ferdinand, 1526 Februar 22, Ofen....","fid":"tocTable"}]},{"docId":"listplace","docUri":"listplace.html","score":36,"contexts":[{"form":"Ludwig","weight":"1","pos":913,"context":"Ferdinand an Kg. <mark>Ludwig<\/mark> II., 1523 Dezember 19, Nürnberg.","fid":"tocTable"},{"form":"Ludwig","weight":"1","pos":933,"context":"Ferdinand an Kg <mark>Ludwig<\/mark> II., 1523 Dezember 6, Nürnberg.","fid":"tocTable"},{"form":"Ludwig","weight":"1","pos":938,"context":"Ferdinand an <mark>Ludwig<\/mark> II., 1524 April 16, Nürnberg.","fid":"tocTable"},{"form":"Ludwig","weight":"1","pos":943,"context":"Ferdinand an <mark>Ludwig<\/mark> II., 1524 April 16, Nürnberg.","fid":"tocTable"},{"form":"Ludwig","weight":"1","pos":988,"context":"Ferdinand an <mark>Ludwig<\/mark> II., 1524 Februar 18, Nürnberg.","fid":"tocTable"},{"form":"Ludwig","weight":"1","pos":1951,"context":"<mark>Ludwig<\/mark> II. an Ferdinand, 1522 Dezember 10, Prag....","fid":"tocTable"},{"form":"Ludwig","weight":"1","pos":2407,"context":"Ferdinand an <mark>Ludwig<\/mark> II., 1525 Oktober 1, Tübingen.","fid":"tocTable"},{"form":"Ludwig","weight":"1","pos":2417,"context":"Ferdinand an <mark>Ludwig<\/mark>, 1526 März 26, Tübingen.","fid":"tocTable"},{"form":"Ludwig","weight":"1","pos":2486,"context":"<mark>Ludwig<\/mark> II. an Ferdinand, 1522 Dezember 10, Prag....","fid":"tocTable"},{"form":"Ludwig","weight":"1","pos":2584,"context":"<mark>Ludwig<\/mark> II. an Ferdinand, 1523 Juni 20, Ofen....","fid":"tocTable"},{"form":"Ludwig","weight":"1","pos":2589,"context":"<mark>Ludwig<\/mark> an Ferdinand, 1525 August 24, Ofen.","fid":"tocTable"},{"form":"Ludwig","weight":"1","pos":2595,"context":"Ferdinand an <mark>Ludwig<\/mark> II., 1525 Oktober 1, Tübingen.","fid":"tocTable"},{"form":"Ludwig","weight":"1","pos":2600,"context":"Ferdinand an <mark>Ludwig<\/mark> II., 1525 Oktober 1, Tübingen.","fid":"tocTable"},{"form":"Ludwig","weight":"1","pos":2605,"context":"Ferdinand an Kg. <mark>Ludwig<\/mark> II., 1523 Dezember 19, Nürnberg.","fid":"tocTable"},{"form":"Ludwig","weight":"1","pos":2640,"context":"Ferdinand an Kg. <mark>Ludwig<\/mark> II., 1523 Dezember 19, Nürnberg.","fid":"tocTable"},{"form":"Ludwig","weight":"1","pos":3142,"context":"<mark>Ludwig<\/mark> II. an Ferdinand, 1526 Mai 29, Ofen....","fid":"tocTable"},{"form":"Ludwig","weight":"1","pos":3148,"context":"<mark>Ludwig<\/mark> II. an Ferdinand, 1526 Mai 29, Ofen....","fid":"tocTable"},{"form":"Ludwig","weight":"1","pos":3173,"context":"<mark>Ludwig<\/mark> II. an Ferdinand, 1523 Juni 20, Ofen....","fid":"tocTable"},{"form":"Ludwig","weight":"1","pos":3178,"context":"<mark>Ludwig<\/mark> II. an Ferdinand, 1526 Juni 6, Ofen....","fid":"tocTable"},{"form":"Ludwig","weight":"1","pos":3183,"context":"<mark>Ludwig<\/mark> an Ferdinand, 1525 August 24, Ofen.","fid":"tocTable"},{"form":"Ludwig","weight":"1","pos":3194,"context":"Ferdinand an <mark>Ludwig<\/mark> II., 1525 Oktober 1, Tübingen.","fid":"tocTable"},{"form":"Ludwig","weight":"1","pos":3198,"context":"<mark>Ludwig<\/mark> II. an Ferdinand, 1526 Juli 15, Ofen....","fid":"tocTable"},{"form":"Ludwig","weight":"1","pos":3203,"context":"<mark>Ludwig<\/mark> II. an Ferdinand, 1526 Juli 15, Ofen....","fid":"tocTable"},{"form":"Ludwig","weight":"1","pos":3213,"context":"<mark>Ludwig<\/mark> II. an Ferdinand, 1526 Februar 22, Ofen....","fid":"tocTable"},{"form":"Ludwig","weight":"1","pos":3407,"context":"Ferdinand an <mark>Ludwig<\/mark> II., 1525 Oktober 1, Tübingen.","fid":"tocTable"},{"form":"Ludwig","weight":"1","pos":3897,"context":"<mark>Ludwig<\/mark> II. an Ferdinand, 1526 Juli 15, Ofen....","fid":"tocTable"},{"form":"Ludwig","weight":"1","pos":4205,"context":"<mark>Ludwig<\/mark> II. an Ferdinand, 1523 Juni 20, Ofen....","fid":"tocTable"},{"form":"Ludwig","weight":"1","pos":4211,"context":"<mark>Ludwig<\/mark> II. an Ferdinand, 1523 Juni 20, Ofen....","fid":"tocTable"},{"form":"Ludwig","weight":"1","pos":4252,"context":"<mark>Ludwig<\/mark> II. an Ferdinand, 1526 Juni 6, Ofen....","fid":"tocTable"},{"form":"Ludwig","weight":"1","pos":4258,"context":"<mark>Ludwig<\/mark> II. an Ferdinand, 1526 Juni 6, Ofen....","fid":"tocTable"},{"form":"Ludwig","weight":"1","pos":4266,"context":"Ferdinand an <mark>Ludwig<\/mark> II., 1525 Oktober 1, Tübingen.","fid":"tocTable"},{"form":"Ludwig","weight":"1","pos":4272,"context":"Ferdinand an <mark>Ludwig<\/mark> II., 1525 Oktober 1, Tübingen.","fid":"tocTable"},{"form":"Ludwig","weight":"1","pos":4589,"context":"<mark>Ludwig<\/mark> II. an Ferdinand, 1523 April 24, Neutra....","fid":"tocTable"},{"form":"Ludwig","weight":"1","pos":4595,"context":"<mark>Ludwig<\/mark> II. an Ferdinand, 1523 April 24, Neutra....","fid":"tocTable"},{"form":"Ludwig","weight":"1","pos":4662,"context":"Ferdinand an <mark>Ludwig<\/mark>, 1526 März 26, Tübingen.","fid":"tocTable"},{"form":"Ludwig","weight":"1","pos":4869,"context":"Ferdinand an <mark>Ludwig<\/mark> II., 1524 Februar 18, Nürnberg.","fid":"tocTable"}]},{"docId":"toc","docUri":"toc.html","score":15,"contexts":[{"form":"Ludwig","weight":"1","pos":63,"context":"<mark>Ludwig<\/mark> II. an Ferdinand, 1526 Februar 22, Ofen....","fid":"tocTable"},{"form":"Ludwig","weight":"1","pos":202,"context":"<mark>Ludwig<\/mark> II. an Ferdinand, 1523 April 24, Neutra....","fid":"tocTable"},{"form":"Ludwig","weight":"1","pos":665,"context":"Ferdinand an <mark>Ludwig<\/mark>, 1526 März 26, Tübingen.","fid":"tocTable"},{"form":"Ludwig","weight":"1","pos":684,"context":"<mark>Ludwig<\/mark> II. an Ferdinand, 1526 Juli 15, Ofen....","fid":"tocTable"},{"form":"Ludwig","weight":"1","pos":712,"context":"<mark>Ludwig<\/mark> II. an Ferdinand, 1523 Juni 20, Ofen....","fid":"tocTable"},{"form":"Ludwig","weight":"1","pos":890,"context":"<mark>Ludwig<\/mark> II. an Ferdinand, 1526 Mai 29, Ofen....","fid":"tocTable"},{"form":"Ludwig","weight":"1","pos":910,"context":"<mark>Ludwig<\/mark> an Ferdinand, 1525 August 24, Ofen.","fid":"tocTable"},{"form":"Ludwig","weight":"1","pos":978,"context":"<mark>Ludwig<\/mark> II. an Ferdinand, 1526 Juni 6, Ofen....","fid":"tocTable"},{"form":"Ludwig","weight":"1","pos":1062,"context":"<mark>Ludwig<\/mark> an Ferdinand, 1524 Jänner 14.","fid":"tocTable"},{"form":"Ludwig","weight":"1","pos":1075,"context":"Ferdinand an <mark>Ludwig<\/mark> II., 1524 Februar 18, Nürnberg.","fid":"tocTable"},{"form":"Ludwig","weight":"1","pos":1096,"context":"Ferdinand an Kg <mark>Ludwig<\/mark> II., 1523 Dezember 6, Nürnberg.","fid":"tocTable"},{"form":"Ludwig","weight":"1","pos":1374,"context":"Ferdinand an Kg. <mark>Ludwig<\/mark> II., 1523 Dezember 19, Nürnberg.","fid":"tocTable"},{"form":"Ludwig","weight":"1","pos":1630,"context":"Ferdinand an <mark>Ludwig<\/mark> II., 1525 Oktober 1, Tübingen.","fid":"tocTable"},{"form":"Ludwig","weight":"1","pos":1699,"context":"Ferdinand an <mark>Ludwig<\/mark> II., 1524 April 16, Nürnberg.","fid":"tocTable"},{"form":"Ludwig","weight":"1","pos":1770,"context":"<mark>Ludwig<\/mark> II. an Ferdinand, 1522 Dezember 10, Prag....","fid":"tocTable"}]},{"docId":"A049","docUri":"A049.html","score":6,"contexts":[{"form":"Ludwig","weight":"2","pos":13,"context":"Ferdinand an Kg <mark>Ludwig<\/mark> II., 1523 Dezember 6, Nürnberg.","fid":"page"},{"form":"Ludwig","weight":"1","pos":19,"context":"Ferdinand an Kg <mark>Ludwig<\/mark> II.","fid":"d53e47"},{"form":"Ludwig","weight":"1","pos":47,"context":"...zu erobern. Dies wäre ein unvergleichliches Unglück für <mark>Ludwig<\/mark> und seine Länder. Cum autem nos proximo anno...","fid":"d53e60"},{"form":"Ludwig","weight":"1","pos":193,"context":"...conquer it. This would be an incomparable misfortune for <mark>Ludwig<\/mark> and his countries. Cum autem nos proximo anno...","fid":"d53e85"},{"form":"Ludwig","weight":"1","pos":291,"context":".... He hopes this will be the case with <mark>Ludwig<\/mark>.","fid":"d53e85"}]},{"docId":"A018","docUri":"A018.html","score":4,"contexts":[{"form":"Ludwig","weight":"1","pos":1298,"context":"Kg. <mark>Ludwig<\/mark> scheint aber trotzdem die Absicht gehabt zu haben, samt...","fid":"d22e362"},{"form":"Ludwig","weight":"1","pos":1377,"context":"...den Gfen. Johann Hardegg und Balbi an Kg. <mark>Ludwig<\/mark> sandte, um unter anderem die Absendung böhmischer Oratoren...","fid":"d22e362"},{"form":"Ludwig","weight":"1","pos":1397,"context":"...für tunlicher, um Reichshilfe zu erlangen, wenn <mark>Ludwig<\/mark> selbst nach Nürnberg käme. Doch wollten weder die...","fid":"d22e362"},{"form":"Ludwig","weight":"1","pos":1683,"context":"...3, S. 800. Darnach hat F dem Kf. <mark>Ludwig<\/mark> bereits am 4. Juni geschrieben und ihn zum Eintritt...","fid":"d22e511"}]},{"docId":"A040","docUri":"A040.html","score":5,"contexts":[{"form":"Ludwig","weight":"2","pos":12,"context":"<mark>Ludwig<\/mark> II. an Ferdinand, 1523 Juni 20, Ofen....","fid":"page"},{"form":"Ludwig","weight":"1","pos":18,"context":"<mark>Ludwig<\/mark> II. an Ferdinand.","fid":"d44e47"},{"form":"Ludwigs","weight":"1","pos":63,"context":"...Erlaubnis zu widerrufen. Nun sind diese Briefe auf <mark>Ludwigs<\/mark> Bitte hin von F bestätigt worden und nichts ist...","fid":"d44e60"},{"form":"Ludwig's","weight":"1","pos":188,"context":"...Now these letters have been confirmed by F at <mark>Ludwig's<\/mark> request and nothing has happened, cur huiusmodi privilegia...","fid":"d44e139"}]},{"docId":"A188","docUri":"A188.html","score":5,"contexts":[{"form":"Ludwig","weight":"2","pos":13,"context":"Ferdinand an <mark>Ludwig<\/mark>, 1526 März 26, Tübingen.","fid":"page"},{"form":"Ludwig","weight":"1","pos":20,"context":"Ferdinand an <mark>Ludwig<\/mark>.","fid":"d191e47"},{"form":"Ludwig","weight":"1","pos":210,"context":"...deutscher Sprache abgefaßt ist, während sonst die Korrespondenz zwischen <mark>Ludwig<\/mark> II. von Ungarn und F lateinisch geführt worden ist....","fid":"d191e108"},{"form":"Ludwig","weight":"1","pos":250,"context":"...damit. Mit Rücksicht auf die drohende Türkengefahr befahl Kg. <mark>Ludwig<\/mark> dem Ban, in Kroatien zu bleiben und an...","fid":"d191e116"}]},{"docId":"A155","docUri":"A155.html","score":5,"contexts":[{"form":"Ludwig","weight":"2","pos":13,"context":"Ferdinand an <mark>Ludwig<\/mark> II., 1525 Oktober 1, Tübingen.","fid":"page"},{"form":"Ludwig","weight":"1","pos":20,"context":"Ferdinand an <mark>Ludwig<\/mark> II.","fid":"d158e47"},{"form":"Ludwig","weight":"1","pos":324,"context":"...anderen Tages (ebenda, Konzept). Nichtsdestoweniger drängte <mark>Ludwig<\/mark> in seinem Briefe vom 8. November an die Regenten...","fid":"d158e165"},{"form":"Ludwig","weight":"1","pos":335,"context":"...Original). Aus späteren Briefentwürfen geht hervor, daß <mark>Ludwig<\/mark> die Frist auf den Andreastag (30. November) erstreckt...","fid":"d158e165"}]},{"docId":"A202","docUri":"A202.html","score":4,"contexts":[{"form":"Ludwig","weight":"2","pos":12,"context":"<mark>Ludwig<\/mark> II. an Ferdinand, 1526 Juni 6, Ofen....","fid":"page"},{"form":"Ludwig","weight":"1","pos":19,"context":"<mark>Ludwig<\/mark> II. an Ferdinand.","fid":"d205e47"},{"form":"Ludwig","weight":"1","pos":490,"context":"Am 2. Juni versammelte <mark>Ludwig<\/mark> II. die ungarischen Herren und die auswärtigen Gesandten (des...","fid":"d205e193"}]},{"docId":"A052","docUri":"A052.html","score":3,"contexts":[{"form":"Ludwig","weight":"2","pos":13,"context":"Ferdinand an Kg. <mark>Ludwig<\/mark> II., 1523 Dezember 19, Nürnberg.","fid":"page"},{"form":"Ludwig","weight":"1","pos":19,"context":"Ferdinand an Kg. <mark>Ludwig<\/mark> II.","fid":"d56e47"}]},{"docId":"A055","docUri":"A055.html","score":3,"contexts":[{"form":"Ludwig","weight":"2","pos":12,"context":"<mark>Ludwig<\/mark> an Ferdinand, 1524 Jänner 14.","fid":"page"},{"form":"Ludwig","weight":"1","pos":17,"context":"<mark>Ludwig<\/mark> an Ferdinand.","fid":"d59e44"}]},{"docId":"A200","docUri":"A200.html","score":3,"contexts":[{"form":"Ludwig","weight":"2","pos":12,"context":"<mark>Ludwig<\/mark> II. an Ferdinand, 1526 Mai 29, Ofen....","fid":"page"},{"form":"Ludwig","weight":"1","pos":19,"context":"<mark>Ludwig<\/mark> II. an Ferdinand.","fid":"d203e47"}]},{"docId":"A233","docUri":"A233.html","score":2,"contexts":[{"form":"Ludwigs","weight":"1","pos":27,"context":"Beileid anläßlich Kg. <mark>Ludwigs<\/mark> Tod. Verspricht ihr seine Hilfe. Sein und...","fid":"d236e60"},{"form":"Ludwigs","weight":"1","pos":389,"context":"...9. September die erste sichere Nachricht vom Tode Kg. <mark>Ludwigs<\/mark> erhalten haben, da er noch am Vortage (Nr. A...","fid":"d236e201"}]},{"docId":"A026","docUri":"A026.html","score":2,"contexts":[{"form":"Ludwigs","weight":"1","pos":2393,"context":"Über die trostlosen Zustände in den Reichen Kg. <mark>Ludwigs<\/mark> vgl. Stoegmann, S. 166f.; W. Fraknói...","fid":"d30e550"},{"form":"Ludwig","weight":"1","pos":2569,"context":"...für seine zahlreichen böhmischen Lehen die Lehenspflicht gegenüber Kg. <mark>Ludwig<\/mark> anzuerkennen, weswegen die böhmischen Stände fortwährend zum Kriege...","fid":"d30e574"}]},{"docId":"A148","docUri":"A148.html","score":3,"contexts":[{"form":"Ludwig","weight":"2","pos":12,"context":"<mark>Ludwig<\/mark> an Ferdinand, 1525 August 24, Ofen.","fid":"page"},{"form":"Ludwig","weight":"1","pos":19,"context":"<mark>Ludwig<\/mark> an Ferdinand.","fid":"d151e47"}]},{"docId":"A057","docUri":"A057.html","score":3,"contexts":[{"form":"Ludwig","weight":"2","pos":13,"context":"Ferdinand an <mark>Ludwig<\/mark> II., 1524 Februar 18, Nürnberg.","fid":"page"},{"form":"Ludwig","weight":"1","pos":19,"context":"Ferdinand an <mark>Ludwig<\/mark> II.","fid":"d61e47"}]},{"docId":"A063","docUri":"A063.html","score":3,"contexts":[{"form":"Ludwig","weight":"2","pos":13,"context":"Ferdinand an <mark>Ludwig<\/mark> II., 1524 April 16, Nürnberg.","fid":"page"},{"form":"Ludwig","weight":"1","pos":19,"context":"Ferdinand an <mark>Ludwig<\/mark> II.","fid":"d67e47"}]},{"docId":"A210","docUri":"A210.html","score":3,"contexts":[{"form":"Ludwig","weight":"2","pos":12,"context":"<mark>Ludwig<\/mark> II. an Ferdinand, 1526 Juli 15, Ofen....","fid":"page"},{"form":"Ludwig","weight":"1","pos":19,"context":"<mark>Ludwig<\/mark> II. an Ferdinand.","fid":"d213e47"}]},{"docId":"A031","docUri":"A031.html","score":3,"contexts":[{"form":"Ludwig","weight":"2","pos":12,"context":"<mark>Ludwig<\/mark> II. an Ferdinand, 1523 April 24, Neutra....","fid":"page"},{"form":"Ludwig","weight":"1","pos":18,"context":"<mark>Ludwig<\/mark> II. an Ferdinand.","fid":"d35e47"}]},{"docId":"A239","docUri":"A239.html","score":2,"contexts":[{"form":"Ludwigs","weight":"1","pos":74,"context":"...7. Einfall der Türken in Ungarn. Tod Kg. <mark>Ludwigs<\/mark>. Maria ist in Preßburg. 8. Zapolyas Bemühungen...","fid":"d242e60"},{"form":"Ludwigs","weight":"1","pos":109,"context":"...Falle weiteren Vordringens der Türken steht ihm vielleicht Kg. <mark>Ludwigs<\/mark> Schicksal bevor. Bittet um ausführlichen Rat von seiten...","fid":"d242e60"}]},{"docId":"A136","docUri":"A136.html","score":2,"contexts":[{"form":"Ludwig","weight":"1","pos":101,"context":"...den Landen F’s und denen der Hgge Wilhelm und <mark>Ludwig<\/mark> von Bayern, ungehindert. 15. Die aufständischen Bauern...","fid":"d139e60"},{"form":"Ludwig","weight":"1","pos":2866,"context":"...Gf Christoph Frangipani befreit, wofür er von Kg <mark>Ludwig<\/mark> den Titel „Verteidiger und Beschützer des Königreiches Dalmatien...","fid":"d139e641"}]},{"docId":"A025","docUri":"A025.html","score":3,"contexts":[{"form":"Ludwig","weight":"2","pos":12,"context":"<mark>Ludwig<\/mark> II. an Ferdinand, 1522 Dezember 10, Prag....","fid":"page"},{"form":"Ludwig","weight":"1","pos":18,"context":"<mark>Ludwig<\/mark> II. an Ferdinand.","fid":"d29e47"}]},{"docId":"A232","docUri":"A232.html","score":2,"contexts":[{"form":"Ludwig","weight":"1","pos":32,"context":"...um Ungarn zu helfen. Erfreut darüber, daß Kg. <mark>Ludwig<\/mark> entkommen ist.","fid":"d235e60"},{"form":"Ludwigs","weight":"1","pos":348,"context":"...den Eingeweihten in Ungarn die Kenntnis von dem Aufenthalte <mark>Ludwigs<\/mark> II. unsicher, bis ein Kämmerer des Kgs die...","fid":"d235e180"}]},{"docId":"A185","docUri":"A185.html","score":3,"contexts":[{"form":"Ludwig","weight":"2","pos":12,"context":"<mark>Ludwig<\/mark> II. an Ferdinand, 1526 Februar 22, Ofen....","fid":"page"},{"form":"Ludwig","weight":"1","pos":19,"context":"<mark>Ludwig<\/mark> II. an Ferdinand.","fid":"d188e47"}]},{"docId":"A237","docUri":"A237.html","score":1,"contexts":[{"form":"Ludwigs","weight":"1","pos":28,"context":"1. Seine Heise nach Linz. Niederlage Kg. <mark>Ludwigs<\/mark> gegen die Türken, Gefahren für Österreich. Maria...","fid":"d240e60"}]},{"docId":"A201","docUri":"A201.html","score":1,"contexts":[{"form":"Ludwigs","weight":"1","pos":43,"context":"...Ungarn 2. Original, gleichlautend mit dem obigen Briefe <mark>Ludwigs<\/mark> II. Die eigenhändige Unterfertigung lautet: E. S. V....","fid":"d204e75"}]},{"docId":"A234","docUri":"A234.html","score":1,"contexts":[{"form":"Ludwigs","weight":"1","pos":685,"context":"...Grundlage seiner und seiner Gattin Ansprüche auf das Erbe <mark>Ludwigs<\/mark> II. Huber, Gesch. Österr. 3, S....","fid":"d237e180"}]},{"docId":"A129","docUri":"A129.html","score":1,"contexts":[{"form":"Ludwig","weight":"1","pos":269,"context":"...hervorgeht, wurde Herberstein am 3. März zu Kg. <mark>Ludwig<\/mark> gesandt, „belanngendt frantzosische practikhn durch Fridrichn Gonsaga...","fid":"d132e146"}]},{"docId":"A014","docUri":"A014.html","score":1,"contexts":[{"form":"Ludwigs","weight":"1","pos":306,"context":"...am 7. November 1520 zwischen K und den Gesandten <mark>Ludwigs<\/mark> II. von Ungarn, Balbi und Sárkány, geschlossen...","fid":"d18e122"}]},{"docId":"A073","docUri":"A073.html","score":1,"contexts":[{"form":"Ludwigs","weight":"1","pos":317,"context":"...in Firnhaber, Vincenco Guidotos Gesandtschaft am Hofe Kg <mark>Ludwigs<\/mark> von Ungarn (1523—1525) in Quellen...","fid":"d77e68"}]},{"docId":"A122","docUri":"A122.html","score":1,"contexts":[{"form":"Ludwig","weight":"1","pos":846,"context":"...(Jutta), die in erster Ehe den Gfen <mark>Ludwig<\/mark> von Blamont und zwischen 1505 und 1507 den Gfen...","fid":"d125e209"}]},{"docId":"A076","docUri":"A076.html","score":1,"contexts":[{"form":"Ludwig","weight":"1","pos":14856,"context":"Der Kf <mark>Ludwig<\/mark> von der Pfalz hat von Anbeginn an seinem Recht...","fid":"d80e2601"}]},{"docId":"A160","docUri":"A160.html","score":1,"contexts":[{"form":"Ludwig","weight":"1","pos":35,"context":"...vorher aber an M und ihren Gemahl, Kg. <mark>Ludwig<\/mark>, verschiedenes von ihm auszurichten haben.","fid":"d163e65"}]},{"docId":"A252","docUri":"A252.html","score":1,"contexts":[{"form":"Ludwigs","weight":"1","pos":31,"context":"...vom 22. September. Trauer über den Tod Kg. <mark>Ludwigs<\/mark> von Ungarn. Beförderungsart dieses Briefes. 2. Gemeinsamkeit...","fid":"d255e60"}]}]}