{"stem":"mad","instances":[{"docId":"A216","docUri":"A216.html","score":9,"contexts":[{"form":"mad","weight":"1","pos":756,"context":"...guerre que meneroie jusques avoir remis sus et refformé <mark>mad<\/mark>. armée.","fid":"d219e95"},{"form":"mad","weight":"1","pos":1378,"context":"...le passaige ouvert pour vous pouoir aller joindre avec <mark>mad<\/mark>. armée pour cela ne s’excuseroit mon allée en...","fid":"d219e187"},{"form":"mad","weight":"1","pos":2045,"context":"...garder leurs terres, et en tel cas demeurroit <mark>mad<\/mark>. armée libre pour pouoir faire plus de dommaige...","fid":"d219e237"},{"form":"mad","weight":"1","pos":2445,"context":"...necessité que j’ai d’argent et qu’il me fault entretenir <mark>mad<\/mark>. armée de Lombardie et aussi envoyer gens et...","fid":"d219e273"},{"form":"mad","weight":"1","pos":2708,"context":"...oul) Ville-Franche eulx joindre avec <mark>mad<\/mark>. armée, ou, s’il est mieulx, pourront...","fid":"d219e300"},{"form":"mad","weight":"1","pos":2966,"context":"..., mon frere, vous voyez que tant pour <mark>mad<\/mark>. armée que pour envoyer celle de mer avec...","fid":"d219e384"},{"form":"mad","weight":"1","pos":3344,"context":"...devant vous ai escript de ceste matiere et aussi <mark>mad<\/mark>. dame, nostre tante, vous me ferez...","fid":"d219e464"},{"form":"mad","weight":"1","pos":3884,"context":"...les choses que de present s’offrent la necessité de <mark>mad<\/mark>. allée ne pourroit estre plus grande que maintenant...","fid":"d219e582"},{"form":"mad","weight":"1","pos":3950,"context":"...mal aiséz à recouvrer. Et pour ces raisons <mark>mad<\/mark>. allée est tres necessaire et ne la vouldroie...","fid":"d219e582"}]},{"docId":"A169","docUri":"A169.html","score":3,"contexts":[{"form":"mad","weight":"1","pos":82,"context":"...leur sont renouvelléz par les gouverneurs et autres de <mark>mad<\/mark>. cité non seullement au tres grant prejudice et...","fid":"d172e71"},{"form":"mad","weight":"1","pos":115,"context":"...appartient, pourroit succeder la desolacion et perdicion de <mark>mad<\/mark>. cité et seroient contrainctz lesd. de chappitre...","fid":"d172e71"},{"form":"mad","weight":"1","pos":145,"context":"...pis est, m’a aussi esté remonstré que en <mark>mad<\/mark>. cité pululent et sont desia eslevéz plusieurs judices...","fid":"d172e71"}]},{"docId":"A050","docUri":"A050.html","score":3,"contexts":[{"form":"mad","weight":"1","pos":984,"context":"...que j’aie entremis led. de Furstemberch, comme <mark>mad<\/mark>. dame et tante le m’a escript, je...","fid":"d54e161"},{"form":"mad","weight":"1","pos":1321,"context":"...que nulle priere ni requeste depar vous, depar <mark>mad<\/mark>. dame et tante ni depar moi n’a peu...","fid":"d54e240"},{"form":"mad","weight":"1","pos":1694,"context":"...ainsi comme je le pensoie et en escripviz à <mark>mad<\/mark>. dame et tante. Et en effect,...","fid":"d54e302"}]},{"docId":"A046","docUri":"A046.html","score":3,"contexts":[{"form":"mad","weight":"1","pos":959,"context":"...avoit l’homme devers led. personnage, par lequel <mark>mad<\/mark>. dame, nostre tante, auroit toutes nouvelles...","fid":"d50e207"},{"form":"mad","weight":"1","pos":986,"context":"...conte est personnage tel et si bon serviteur que <mark>mad<\/mark>. dame, nostre tante, scet si avons...","fid":"d50e207"},{"form":"mad","weight":"1","pos":1013,"context":"...nouvelles. Parquoi ne sçavons quant à ce advertir <mark>mad<\/mark>. dame, nostre tante, plus avant que...","fid":"d50e207"}]},{"docId":"A056","docUri":"A056.html","score":2,"contexts":[{"form":"mad","weight":"1","pos":1145,"context":"...condempnacion à la forme de l’empire ainsi que par <mark>mad<\/mark>. lectre en allemand je vous escriptz de sorte...","fid":"d60e205"},{"form":"mad","weight":"1","pos":1177,"context":"...que pourra valoir ou temps advenir avec l’execution que <mark>mad<\/mark>. armée d’Ytalie y pourra faire, vous priant...","fid":"d60e205"}]},{"docId":"A069","docUri":"A069.html","score":2,"contexts":[{"form":"mad","weight":"1","pos":449,"context":"..., vouz les possedez en vostre privé nom et <mark>mad<\/mark>. dame, nostre tante, possede lad....","fid":"d73e141"},{"form":"mad","weight":"1","pos":493,"context":"...charge. Et sur ce j’escriptz en semblable à <mark>mad<\/mark>. dame, nostre tante, et principallement qu’elle...","fid":"d73e141"}]},{"docId":"A190","docUri":"A190.html","score":1,"contexts":[{"form":"mad","weight":"1","pos":221,"context":"...la desraciner, diminuer et affaiblir, en actendant <mark>mad<\/mark>. venue, àb) laquelle n’aura faulte...","fid":"d193e88"}]},{"docId":"A036","docUri":"A036.html","score":1,"contexts":[{"form":"mad","weight":"1","pos":1200,"context":"...beaucop de gens de bien et autres, voyant <mark>mad<\/mark>. declaration, ne se oserent monstrer ne faire...","fid":"d40e224"}]},{"docId":"A158","docUri":"A158.html","score":1,"contexts":[{"form":"mad","weight":"1","pos":670,"context":"...pour le grant bien de mes affaires, mais <mark>mad<\/mark>. presence ne peut estre si tost qu’il seroit...","fid":"d161e135"}]},{"docId":"A062","docUri":"A062.html","score":1,"contexts":[{"form":"mad","weight":"1","pos":1318,"context":"...m’advertir à la verité de la somme juste que <mark>mad<\/mark>. portion peut monter pour faire donner ordre aud...","fid":"d66e247"}]},{"docId":"A021","docUri":"A021.html","score":1,"contexts":[{"form":"mad","weight":"1","pos":1299,"context":"...effect, serons content de donner et assigner à <mark>mad<\/mark>. dame et tante austant de rente ordinaire comme...","fid":"d25e286"}]},{"docId":"A117","docUri":"A117.html","score":1,"contexts":[{"form":"mad","weight":"1","pos":383,"context":"...prie tenir la main et en faire responce à <mark>mad<\/mark>. dame, nostre tante.","fid":"d121e151"}]},{"docId":"A122","docUri":"A122.html","score":1,"contexts":[{"form":"mad","weight":"1","pos":701,"context":"...plus me justiffier ai respondu et suis content que <mark>mad<\/mark>. dame et tante commette quatre conseilliers et semblablement...","fid":"d125e88"}]},{"docId":"A143","docUri":"A143.html","score":1,"contexts":[{"form":"mad","weight":"1","pos":358,"context":"...Lutheriens, non faisant aulcune doubte que, actendant <mark>mad<\/mark>. venue, pourvoyerez à l’encontre d’eulx le mieulx...","fid":"d146e81"}]},{"docId":"A254","docUri":"A254.html","score":1,"contexts":[{"form":"mad","weight":"1","pos":464,"context":"...pourrai remedier et garder mond droit, car obstant <mark>mad<\/mark>. necessité le plus grant espoir que j’en ai,...","fid":"d257e82"}]},{"docId":"A252","docUri":"A252.html","score":1,"contexts":[{"form":"mad","weight":"1","pos":515,"context":"...correspondant que meilleur ne pourroit estre, et d’avancer <mark>mad<\/mark>. allée le plus que faire se pourra,...","fid":"d255e113"}]}]}