{"stem":"maulvais","instances":[{"docId":"A143","docUri":"A143.html","score":1,"contexts":[{"form":"maulvaises","weight":"1","pos":296,"context":"Premiers quant au mouvement des Lutheriains et des <mark>maulvaises<\/mark> choses qu’ilz ont faites et est apparant continueront de...","fid":"d146e81"}]},{"docId":"A216","docUri":"A216.html","score":1,"contexts":[{"form":"maulvaises","weight":"1","pos":4398,"context":"...tranquilité en l’empire, qu’est bien necessaire selon les <mark>maulvaises<\/mark> voluntéz que je suis adverti qu’il y a en...","fid":"d219e725"}]}]}