{"stem":"mili","instances":[{"docId":"A140","docUri":"A140.html","score":2,"contexts":[{"form":"mili","weight":"1","pos":624,"context":"...tena 1400o de caballo y tres ó quatro <mark>mili<\/mark> peones, para por sí ó juntamente con algun...","fid":"d143e124"},{"form":"mili","weight":"1","pos":838,"context":"...es en efecto lo de la sal y cient <mark>mili<\/mark> ducados, si fuere posible, perpetuos cada año...","fid":"d143e214"}]},{"docId":"A136","docUri":"A136.html","score":1,"contexts":[{"form":"mili","weight":"1","pos":1958,"context":".... Lo segundo que sea pagado de los cinquenta <mark>mili<\/mark> ducados, de que ha ya espirado el tienpo...","fid":"d139e414"}]}]}