{"stem":"morron","instances":[{"docId":"A157","docUri":"A157.html","score":5,"contexts":[{"form":"Morron","weight":"1","pos":130,"context":"...r, averti, a fait prendre prisonnier Iheronimo <mark>Morron<\/mark>, grant-chancellier du duc de Milan,...","fid":"d160e71"},{"form":"Morron","weight":"1","pos":192,"context":"...jour de nuict led. marquis envoya led. <mark>Morron<\/mark> au chasteau de Pavie par Anthonio de Leyva avec...","fid":"d160e71"},{"form":"Morron","weight":"1","pos":210,"context":"...et, après qu’il fust illecq, dit led. <mark>Morron<\/mark> à icellui Anthonio de Leyva qu’il fit venir led...","fid":"d160e71"},{"form":"Morron","weight":"1","pos":236,"context":"...te tellement que icellui marquis entendoit sçavoir dud. <mark>Morron<\/mark> tout le secret et intelligences qui se desmenoient,...","fid":"d160e71"},{"form":"Morron","weight":"1","pos":388,"context":"...r, tres humblement que, si led. <mark>Morron<\/mark> declairast chose, parquoi me puissies monstrer ung tour...","fid":"d160e71"}]},{"docId":"A167","docUri":"A167.html","score":1,"contexts":[{"form":"Morron","weight":"1","pos":163,"context":"Quant à la prinse de Iheronime <mark>Morron<\/mark>, par mes lettres du 22e d’octobre vous...","fid":"d170e107"}]},{"docId":"A166","docUri":"A166.html","score":1,"contexts":[{"form":"Morron","weight":"1","pos":249,"context":"...par lesquelles se devoit prouver la confession de Jheronime <mark>Morron<\/mark> en ce qui touchoit led. duc, qu’est...","fid":"d169e94"}]}]}