{"stem":"obtenir","instances":[{"docId":"A021","docUri":"A021.html","score":2,"contexts":[{"form":"obtenir","weight":"1","pos":1631,"context":"...commis ad ce ait sceu faire n’a encoires peu <mark>obtenir<\/mark> payement que de 4000 ducas. Parquoi supplions sad...","fid":"d25e354"},{"form":"obtenir","weight":"1","pos":1892,"context":"..., rendront paine à ce que puissions consuivre et <mark>obtenir<\/mark> le contenu en icelle instruction.","fid":"d25e382"}]},{"docId":"A131","docUri":"A131.html","score":1,"contexts":[{"form":"obtenir","weight":"1","pos":362,"context":"...le roi de France, pour plus facilement pouoir <mark>obtenir<\/mark> et occuper lad. duchié et que j’eusse cause...","fid":"d134e73"}]},{"docId":"A029","docUri":"A029.html","score":1,"contexts":[{"form":"obtenir","weight":"1","pos":326,"context":"...que venu en Allemagne, si ne pouviez mieulx <mark>obtenir<\/mark> desd. Veniciens et fere aultre meilleur appoinctement avec...","fid":"d33e74"}]},{"docId":"A143","docUri":"A143.html","score":1,"contexts":[{"form":"obtenir","weight":"1","pos":1030,"context":"...par led. Salinas, et desia avoie fait <mark>obtenir<\/mark> son saulfconduit pour le faire passer par terre et...","fid":"d146e148"}]},{"docId":"A149","docUri":"A149.html","score":1,"contexts":[{"form":"obtenir","weight":"1","pos":627,"context":"...paix, et si autre chose ne se pouoit <mark>obtenir<\/mark> à mon prouffit, au moins que je eusse...","fid":"d152e189"}]},{"docId":"A212","docUri":"A212.html","score":1,"contexts":[{"form":"obtenir","weight":"1","pos":373,"context":"...leur ai sceu faire presenté, n’ai riens peu <mark>obtenir<\/mark> d’eulx et en effect les treuve si rebours et...","fid":"d215e85"}]},{"docId":"A216","docUri":"A216.html","score":1,"contexts":[{"form":"obtenir","weight":"1","pos":2384,"context":"...preparitives pour donner plus de chaleur et faveur à <mark>obtenir<\/mark> led. appoinctement, si faire se peult ou...","fid":"d219e273"}]},{"docId":"A034","docUri":"A034.html","score":1,"contexts":[{"form":"obtenir","weight":"1","pos":99,"context":"..., laquelle ilz entendent à l’aide de dieu brief <mark>obtenir<\/mark>. Et est led. Francisque parti secretement et...","fid":"d38e71"}]},{"docId":"A238","docUri":"A238.html","score":1,"contexts":[{"form":"obtenir","weight":"1","pos":380,"context":"...que le roi de France avoit fait arrester et <mark>obtenir<\/mark> maistre Guillaume des Barres à son passaige à Bayonne...","fid":"d241e172"}]}]}