{"stem":"ouvertur","instances":[{"docId":"A207","docUri":"A207.html","score":3,"contexts":[{"form":"ouvertures","weight":"1","pos":447,"context":"...mandé que de sa part ilz ne condescendissent aux <mark>ouvertures<\/mark>f) que le roi et sad. mere...","fid":"d210e159"},{"form":"ouverture","weight":"1","pos":482,"context":"...avant qu’ilz eussent à faire une autre plus raisonable <mark>ouverture<\/mark> et plus honorable pour l’empereur et eulx que celle...","fid":"d210e159"},{"form":"ouverture","weight":"1","pos":518,"context":"...ilz dit, puis que l’empereur ne trouvast leur <mark>ouverture<\/mark>f) bonne, laquelle toutesvoies estoit tres soustenante...","fid":"d210e159"}]},{"docId":"A252","docUri":"A252.html","score":1,"contexts":[{"form":"ouverture","weight":"1","pos":1681,"context":"..., lequel de sa part ne m’a parlé d’aulcune <mark>ouverture<\/mark>, ni moyen de paix, seullement m’a mercie...","fid":"d255e278"}]}]}