{"stem":"passau","instances":[{"docId":"A166","docUri":"A166.html","score":2,"contexts":[{"form":"Passau","weight":"1","pos":47,"context":"...Absicht des EB’s von Salzburg, den B. von <mark>Passau<\/mark> zum Koadjutor zu nehmen, muß vereitelt werden. 8....","fid":"d169e60"},{"form":"Passau","weight":"1","pos":104,"context":"...Archbishop of Salzburg's plan to make the Bishop of <mark>Passau<\/mark> his coadjutor must be thwarted. 8. The Archbishop...","fid":"d169e66"}]},{"docId":"A050","docUri":"A050.html","score":1,"contexts":[{"form":"Passau","weight":"1","pos":3328,"context":"...von dort über Wien usw., Linz usw., <mark>Passau<\/mark> nach Regensburg und von da nach Nürnberg führte....","fid":"d54e631"}]},{"docId":"listperson","docUri":"listperson.html","score":1,"contexts":[{"form":"Passau","weight":"1","pos":5665,"context":"Ernst, Herzog von Bayern, Administrator des Bistums <mark>Passau<\/mark>","fid":"tocTable"}]},{"docId":"listplace","docUri":"listplace.html","score":1,"contexts":[{"form":"Passau","weight":"1","pos":4829,"context":"<mark>Passau<\/mark>","fid":"tocTable"}]}]}