{"stem":"pösing","instances":[{"docId":"A155","docUri":"A155.html","score":2,"contexts":[{"form":"Pösing","weight":"1","pos":404,"context":"...Die Ausschreitungen und Raubzüge der Leute des Gfen von <mark>Pösing<\/mark> in das österreichische Gebiet des Gfen Johann von Lamberg...","fid":"d158e165"},{"form":"Pösings","weight":"1","pos":419,"context":"...von Preßburg ungesühnt. Desgleichen blieb das erpresserische Vorgehen <mark>Pösings<\/mark> gegen einen nach Österreich ziehenden bayrischen Kaufmann, ferner...","fid":"d158e165"}]}]}