{"stem":"saxen","instances":[{"docId":"A117","docUri":"A117.html","score":4,"contexts":[{"form":"Saxen","weight":"1","pos":403,"context":".... Et pour ce qu’il a maigrement besoingné en <mark>Saxen<\/mark>, je suis en propoz y renvoyer ung autre...","fid":"d121e165"},{"form":"Saxen","weight":"1","pos":414,"context":"...renvoyer ung autre pour satisfaire aux ducz dud. <mark>Saxen<\/mark>. Sur quoi vous prie m’escripre vostre advis et...","fid":"d121e165"},{"form":"Saxen","weight":"1","pos":913,"context":"...lettres, touchant son besoingne avec les ducz de <mark>Saxen<\/mark> et en Allemaigne, que j’eusse bien voulsu estre...","fid":"d121e219"},{"form":"Saxen","weight":"1","pos":961,"context":"...de la nation Allemande vers lesd. ducz de <mark>Saxen<\/mark>, car je desire bien les contenter et satisfaire...","fid":"d121e219"}]},{"docId":"A124","docUri":"A124.html","score":2,"contexts":[{"form":"Saxen","weight":"1","pos":580,"context":"...vous ai envoyé, depuis le duc Fredrick de <mark>Saxen<\/mark> le m’a mandé. Et affin que vous,...","fid":"d127e219"},{"form":"Saxen","weight":"1","pos":645,"context":"...quant au propos, où estes d’envoyer quelcun en <mark>Saxen<\/mark> et dont demandez, monsr, mon advis...","fid":"d127e246"}]},{"docId":"A116","docUri":"A116.html","score":2,"contexts":[{"form":"Saxen","weight":"1","pos":235,"context":"...gens de bien, voire du mesme duc de <mark>Saxen<\/mark> et icelle eue la vous envoier signée et selée...","fid":"d120e76"},{"form":"Saxen","weight":"1","pos":254,"context":"...suplie aussy treshumblement en escripre aud. duc de <mark>Saxen<\/mark> et à quelque aultre personaige que Salinas vous denommera...","fid":"d120e76"}]},{"docId":"A021","docUri":"A021.html","score":2,"contexts":[{"form":"Saxen","weight":"1","pos":759,"context":"..., comme avions envoyé vers le duc George de <mark>Saxen<\/mark> pour ensuivant le traicté, fait avec sad....","fid":"d25e171"},{"form":"Saxen","weight":"1","pos":2459,"context":"...mte, le conte Palatin et duc de <mark>Saxen<\/mark> se vouldront entremectre d’icellui comme vicaires de l’empire....","fid":"d25e510"}]},{"docId":"A142","docUri":"A142.html","score":1,"contexts":[{"form":"Saxen","weight":"1","pos":650,"context":"...allé de vie à mort le duc Frederick de <mark>Saxen<\/mark>, et semblablement par tout les pays de Saxonie...","fid":"d145e179"}]},{"docId":"A036","docUri":"A036.html","score":1,"contexts":[{"form":"Saxen","weight":"1","pos":1556,"context":"...debvroit rescripre et envoyer vers led. duc de <mark>Saxen<\/mark>, ce que l’on m’a escript depuis mon partement...","fid":"d40e315"}]},{"docId":"A026","docUri":"A026.html","score":1,"contexts":[{"form":"Saxen","weight":"1","pos":1153,"context":"Quant au duc George de <mark>Saxen<\/mark>, je vous avertis monsr que lui tant...","fid":"d30e272"}]},{"docId":"A085","docUri":"A085.html","score":1,"contexts":[{"form":"Saxen","weight":"1","pos":385,"context":"...l’on certiffié doivent envoyer leurs ambassadeurs les duc de <mark>Saxen<\/mark>, marquis Joachin de Brandeburg et conte Palatin,...","fid":"d89e132"}]},{"docId":"A062","docUri":"A062.html","score":1,"contexts":[{"form":"Saxen","weight":"1","pos":1038,"context":"...desmaintenant et aussi le payement du duc George de <mark>Saxen<\/mark>, comme vostre lectre le contient, mais je...","fid":"d66e204"}]},{"docId":"A222","docUri":"A222.html","score":1,"contexts":[{"form":"Saxen","weight":"1","pos":135,"context":"...desolacion qu’elle est presentement, car le duc de <mark>Saxen<\/mark> et lantgrave von Essen ensemble tous leurs serviteurs sont...","fid":"d225e101"}]},{"docId":"A250","docUri":"A250.html","score":1,"contexts":[{"form":"Saxen","weight":"1","pos":414,"context":"...que le roi de Polonie et les ducz de <mark>Saxen<\/mark> et de Baviere ont faitz pour parvenir à ced...","fid":"d253e142"}]},{"docId":"A083","docUri":"A083.html","score":1,"contexts":[{"form":"Saxen","weight":"1","pos":129,"context":"...aura besoingné au fait de Dannemark et aussi de <mark>Saxen<\/mark>, car le mariage de nostred. Seur,...","fid":"d87e77"}]},{"docId":"A103","docUri":"A103.html","score":1,"contexts":[{"form":"Saxen","weight":"1","pos":326,"context":"L’on veult dire que le duc de <mark>Saxen<\/mark> a fait quelque confederation avec les 72 villes de...","fid":"d107e127"}]},{"docId":"A073","docUri":"A073.html","score":1,"contexts":[{"form":"Saxen","weight":"1","pos":955,"context":"...deux cens mil florins d’or au duc George de <mark>Saxen<\/mark>, je vous supplie monsr que le plustost...","fid":"d77e209"}]},{"docId":"A102","docUri":"A102.html","score":1,"contexts":[{"form":"Saxen","weight":"1","pos":399,"context":"...instructions contiennent en caz que lesd. ducz de <mark>Saxen<\/mark> voulsissent entendre au mariaige de la fille dud....","fid":"d106e158"}]},{"docId":"A035","docUri":"A035.html","score":1,"contexts":[{"form":"Saxen","weight":"1","pos":175,"context":"...à ma charge la debte du duc George de <mark>Saxen<\/mark>, nonobstant les grans inconveniens, preiudices et diminucion...","fid":"d39e71"}]},{"docId":"A120","docUri":"A120.html","score":1,"contexts":[{"form":"Saxen","weight":"1","pos":482,"context":"...congnoissance de verité, j’en escriptz au duc de <mark>Saxen<\/mark> et à l’autre personnaige dont m’avez escript et pourrez...","fid":"d124e158"}]}]}