{"stem":"see","instances":[{"docId":"A098","docUri":"A098.html","score":1,"contexts":[{"form":"See","weight":"1","pos":28,"context":"<mark>See<\/mark> no. A105.","fid":"d102e59"}]},{"docId":"A019","docUri":"A019.html","score":1,"contexts":[{"form":"See","weight":"1","pos":29,"context":"<mark>See<\/mark> no. A23.","fid":"d23e67"}]},{"docId":"A227","docUri":"A227.html","score":1,"contexts":[{"form":"see","weight":"1","pos":36,"context":"Is sending Presinger to <mark>see<\/mark> K. In order to contain the proliferation of Lutheranism...","fid":"d230e63"}]},{"docId":"A219","docUri":"A219.html","score":1,"contexts":[{"form":"See","weight":"1","pos":26,"context":"<mark>See<\/mark> no. A221. Possibly identical with no. A...","fid":"d222e59"}]},{"docId":"A017","docUri":"A017.html","score":1,"contexts":[{"form":"See","weight":"1","pos":29,"context":"<mark>See<\/mark> no. A18.","fid":"d21e67"}]},{"docId":"A161","docUri":"A161.html","score":1,"contexts":[{"form":"See","weight":"1","pos":29,"context":"<mark>See<\/mark> no. A164.","fid":"d164e59"}]},{"docId":"A027","docUri":"A027.html","score":1,"contexts":[{"form":"See","weight":"1","pos":29,"context":"<mark>See<\/mark> no. A42.","fid":"d31e67"}]},{"docId":"A055","docUri":"A055.html","score":1,"contexts":[{"form":"See","weight":"1","pos":27,"context":"<mark>See<\/mark> no. A57.","fid":"d59e59"}]},{"docId":"A208","docUri":"A208.html","score":1,"contexts":[{"form":"See","weight":"1","pos":26,"context":"<mark>See<\/mark> no. A212. Possibly identical with no. A...","fid":"d211e59"}]},{"docId":"A045","docUri":"A045.html","score":1,"contexts":[{"form":"See","weight":"1","pos":27,"context":"<mark>See<\/mark> no. A47.","fid":"d49e59"}]},{"docId":"A186","docUri":"A186.html","score":1,"contexts":[{"form":"See","weight":"1","pos":24,"context":"<mark>See<\/mark> no. A189.","fid":"d189e59"}]},{"docId":"A006","docUri":"A006.html","score":1,"contexts":[{"form":"see","weight":"1","pos":48,"context":"...to F's previous two letters. She longs to <mark>see<\/mark> F soon and offers her services.","fid":"d10e64"}]},{"docId":"A058","docUri":"A058.html","score":1,"contexts":[{"form":"see","weight":"1","pos":141,"context":"..., quamvis persona et aliis male dispositum, to <mark>see<\/mark> the Emperor. As Burgo is familiar with both...","fid":"d62e88"}]},{"docId":"A236","docUri":"A236.html","score":1,"contexts":[{"form":"see","weight":"1","pos":381,"context":"...in the matter and report to F or come <mark>see<\/mark> him in person on very important issues.","fid":"d239e158"}]},{"docId":"A115","docUri":"A115.html","score":1,"contexts":[{"form":"See","weight":"1","pos":29,"context":"<mark>See<\/mark> no. A120.","fid":"d119e59"}]},{"docId":"A099","docUri":"A099.html","score":1,"contexts":[{"form":"See","weight":"1","pos":28,"context":"<mark>See<\/mark> no. A105.","fid":"d103e59"}]},{"docId":"A084","docUri":"A084.html","score":1,"contexts":[{"form":"See","weight":"1","pos":27,"context":"<mark>See<\/mark> no. A92.","fid":"d88e59"}]},{"docId":"A044","docUri":"A044.html","score":1,"contexts":[{"form":"See","weight":"1","pos":29,"context":"<mark>See<\/mark> no. A50.","fid":"d48e67"}]},{"docId":"A230","docUri":"A230.html","score":1,"contexts":[{"form":"See","weight":"1","pos":24,"context":"<mark>See<\/mark> no. A234.","fid":"d233e59"}]},{"docId":"A180","docUri":"A180.html","score":1,"contexts":[{"form":"See","weight":"1","pos":24,"context":"<mark>See<\/mark> no. A189.","fid":"d183e59"}]},{"docId":"A181","docUri":"A181.html","score":1,"contexts":[{"form":"See","weight":"1","pos":24,"context":"<mark>See<\/mark> no. A189.","fid":"d184e59"}]},{"docId":"A064","docUri":"A064.html","score":1,"contexts":[{"form":"See","weight":"1","pos":27,"context":"<mark>See<\/mark> no. A67.","fid":"d68e59"}]},{"docId":"A194","docUri":"A194.html","score":1,"contexts":[{"form":"See","weight":"1","pos":24,"context":"<mark>See<\/mark> no. A198.","fid":"d197e59"}]},{"docId":"A203","docUri":"A203.html","score":1,"contexts":[{"form":"See","weight":"1","pos":24,"context":"<mark>See<\/mark> no. A205.","fid":"d206e59"}]},{"docId":"A059","docUri":"A059.html","score":1,"contexts":[{"form":"See","weight":"1","pos":27,"context":"<mark>See<\/mark> no. A70.","fid":"d63e59"}]},{"docId":"A248","docUri":"A248.html","score":1,"contexts":[{"form":"see","weight":"1","pos":46,"context":"...Dr. Markus Beck of Leopoldsdorf and Philipp Preuner to <mark>see<\/mark> Zapolya. Asks her to grant these delegates credence...","fid":"d251e63"}]},{"docId":"A095","docUri":"A095.html","score":1,"contexts":[{"form":"See","weight":"1","pos":30,"context":"<mark>See<\/mark> no. A105.","fid":"d99e65"}]},{"docId":"A086","docUri":"A086.html","score":1,"contexts":[{"form":"See","weight":"1","pos":28,"context":"<mark>See<\/mark> no. A102.","fid":"d90e59"}]},{"docId":"A163","docUri":"A163.html","score":1,"contexts":[{"form":"See","weight":"1","pos":29,"context":"<mark>See<\/mark> no. A164.","fid":"d166e59"}]},{"docId":"A197","docUri":"A197.html","score":1,"contexts":[{"form":"See","weight":"1","pos":24,"context":"<mark>See<\/mark> no. A199.","fid":"d200e59"}]},{"docId":"A135","docUri":"A135.html","score":1,"contexts":[{"form":"See","weight":"1","pos":31,"context":"<mark>See<\/mark> no. A142. Possibly identical with no. A...","fid":"d138e59"}]},{"docId":"A028","docUri":"A028.html","score":1,"contexts":[{"form":"See","weight":"1","pos":29,"context":"<mark>See<\/mark> no. A35.","fid":"d32e67"}]},{"docId":"A022","docUri":"A022.html","score":1,"contexts":[{"form":"See","weight":"1","pos":27,"context":"<mark>See<\/mark> no. A26.","fid":"d26e60"}]},{"docId":"A126","docUri":"A126.html","score":1,"contexts":[{"form":"See","weight":"1","pos":29,"context":"<mark>See<\/mark> no. A129.","fid":"d129e59"}]},{"docId":"A024","docUri":"A024.html","score":1,"contexts":[{"form":"See","weight":"1","pos":27,"context":"<mark>See<\/mark> no. A26.","fid":"d28e59"}]},{"docId":"A215","docUri":"A215.html","score":1,"contexts":[{"form":"See","weight":"1","pos":59,"context":"...Königstein. 7. Rüstungen der Franzosen und Engländer zur <mark>See<\/mark> gegen Neapel.","fid":"d218e60"}]},{"docId":"A114","docUri":"A114.html","score":1,"contexts":[{"form":"see","weight":"1","pos":37,"context":"Asks her to order Hannart to <mark>see<\/mark> F on his way to Poland and pick up...","fid":"d118e63"}]},{"docId":"A110","docUri":"A110.html","score":1,"contexts":[{"form":"See","weight":"1","pos":29,"context":"<mark>See<\/mark> no. A119.","fid":"d114e59"}]},{"docId":"A229","docUri":"A229.html","score":1,"contexts":[{"form":"See","weight":"1","pos":24,"context":"<mark>See<\/mark> no. A234.","fid":"d232e59"}]},{"docId":"A196","docUri":"A196.html","score":1,"contexts":[{"form":"See","weight":"1","pos":24,"context":"<mark>See<\/mark> no. A205.","fid":"d199e59"}]},{"docId":"A113","docUri":"A113.html","score":1,"contexts":[{"form":"See","weight":"1","pos":29,"context":"<mark>See<\/mark> no. A120.","fid":"d117e59"}]},{"docId":"A177","docUri":"A177.html","score":1,"contexts":[{"form":"See","weight":"1","pos":24,"context":"<mark>See<\/mark> no. A178.","fid":"d180e59"}]},{"docId":"A061","docUri":"A061.html","score":1,"contexts":[{"form":"See","weight":"1","pos":27,"context":"<mark>See<\/mark> no. A67.","fid":"d65e59"}]},{"docId":"A043","docUri":"A043.html","score":1,"contexts":[{"form":"See","weight":"1","pos":27,"context":"<mark>See<\/mark> no. A53.","fid":"d47e59"}]},{"docId":"A077","docUri":"A077.html","score":1,"contexts":[{"form":"See","weight":"1","pos":28,"context":"<mark>See<\/mark> no. A104.","fid":"d81e59"}]},{"docId":"A108","docUri":"A108.html","score":1,"contexts":[{"form":"See","weight":"1","pos":29,"context":"<mark>See<\/mark> no. A112.","fid":"d112e59"}]},{"docId":"A213","docUri":"A213.html","score":1,"contexts":[{"form":"See","weight":"1","pos":26,"context":"<mark>See<\/mark> no. A238. Possibly identical with no. A...","fid":"d216e59"}]},{"docId":"A068","docUri":"A068.html","score":1,"contexts":[{"form":"See","weight":"1","pos":27,"context":"<mark>See<\/mark> no. A79.","fid":"d72e59"}]},{"docId":"A020","docUri":"A020.html","score":1,"contexts":[{"form":"See","weight":"1","pos":27,"context":"<mark>See<\/mark> no. A26.","fid":"d24e59"}]},{"docId":"A179","docUri":"A179.html","score":1,"contexts":[{"form":"See","weight":"1","pos":24,"context":"<mark>See<\/mark> no. A183.","fid":"d182e59"}]},{"docId":"A009","docUri":"A009.html","score":1,"contexts":[{"form":"See","weight":"1","pos":27,"context":"<mark>See<\/mark> no. A12.","fid":"d13e60"}]},{"docId":"A176","docUri":"A176.html","score":1,"contexts":[{"form":"See","weight":"1","pos":29,"context":"<mark>See<\/mark> no. A178.","fid":"d179e59"}]},{"docId":"A204","docUri":"A204.html","score":1,"contexts":[{"form":"See","weight":"1","pos":24,"context":"<mark>See<\/mark> no. A216.","fid":"d207e59"}]},{"docId":"A030","docUri":"A030.html","score":1,"contexts":[{"form":"See","weight":"1","pos":27,"context":"<mark>See<\/mark> no. A32.","fid":"d34e59"}]}]}