{"stem":"segniensem","instances":[{"docId":"A031","docUri":"A031.html","score":2,"contexts":[{"form":"Segniensem","weight":"1","pos":39,"context":"...Anzahl deutscher Soldaten die Stadt Zengg (civitatem nostram <mark>Segniensem<\/mark>) angefallen et more hostili depopulato eius agro non...","fid":"d35e60"},{"form":"Segniensem","weight":"1","pos":231,"context":"...Ferdinand attacked the city of Zengg (civitatem nostram <mark>Segniensem<\/mark>) with a not inconsiderable number of German soldiers...","fid":"d35e107"}]}]}