{"stem":"solliciteront","instances":[{"docId":"A021","docUri":"A021.html","score":4,"contexts":[{"form":"solliciteront","weight":"1","pos":1010,"context":"Parquoi <mark>solliciteront<\/mark> iceulx Hemericourt et Salines à toute dilligence, vers...","fid":"d25e214"},{"form":"solliciteront","weight":"1","pos":1081,"context":"...te ensuivant le contract dernierement faict à Bruxelles, <mark>solliciteront<\/mark> icelle assignation, lui remonstrant la grande necessité où...","fid":"d25e228"},{"form":"solliciteront","weight":"1","pos":1389,"context":".... mte. Et de schoses dessusd. <mark>solliciteront<\/mark> lesd. Hemericourt et Salines bien lealement et à...","fid":"d25e300"},{"form":"solliciteront","weight":"1","pos":2143,"context":"...Salines verront ce qu’il requiert et demande, et <mark>solliciteront<\/mark> d’avoir responce et conclusion, disant à sad....","fid":"d25e439"}]}]}