{"stem":"travel","instances":[{"docId":"A216","docUri":"A216.html","score":3,"contexts":[{"form":"travel","weight":"1","pos":167,"context":"...State Diet. 2. Praises F for intending to <mark>travel<\/mark> to Italy. Expresses worry about K's impending travels...","fid":"d219e63"},{"form":"travels","weight":"1","pos":174,"context":"...travel to Italy. Expresses worry about K's impending <mark>travels<\/mark> to Germany and Italy. 3. Advantages of going...","fid":"d219e63"},{"form":"travel","weight":"1","pos":209,"context":"...treaty of Madrid. 6. F's intent to personally <mark>travel<\/mark> to Italy. His concerns regarding this: a)...","fid":"d219e63"}]},{"docId":"A239","docUri":"A239.html","score":2,"contexts":[{"form":"travel","weight":"1","pos":199,"context":"...Despite the Turkish danger, he was willing to <mark>travel<\/mark> to Italy. Sending George of Frundsberg to Augsburg...","fid":"d242e63"},{"form":"travel","weight":"1","pos":266,"context":"...territories remains calm, he is still willing to <mark>travel<\/mark> to Italy. The 100,000 ducats promised would be...","fid":"d242e63"}]},{"docId":"A154","docUri":"A154.html","score":1,"contexts":[{"form":"travel","weight":"1","pos":38,"context":"...of Jehan de Eustzringen, who is planning to <mark>travel<\/mark> to the government of Luxembourg.","fid":"d157e63"}]},{"docId":"A071","docUri":"A071.html","score":1,"contexts":[{"form":"travels","weight":"1","pos":64,"context":"...Switzerland. Demand for contribution. 4. His impending <mark>travels<\/mark> to Austria.","fid":"d75e63"}]},{"docId":"A139","docUri":"A139.html","score":1,"contexts":[{"form":"travel","weight":"1","pos":67,"context":"...part in the Italian war. 3. K's intention to <mark>travel<\/mark> to Italy. F's election to King of the...","fid":"d142e63"}]},{"docId":"A111","docUri":"A111.html","score":1,"contexts":[{"form":"travel","weight":"1","pos":44,"context":"...The Viceroy of Naples has requested that F personally <mark>travel<\/mark> to Italy. Needs Mg's and the King of...","fid":"d115e63"}]},{"docId":"A072","docUri":"A072.html","score":1,"contexts":[{"form":"traveling","weight":"1","pos":150,"context":".... 7. Armament in Ferrette. Reasons he is <mark>traveling<\/mark> to Austria. 8. Is sending 5,000 men to...","fid":"d76e63"}]},{"docId":"A107","docUri":"A107.html","score":1,"contexts":[{"form":"Travel","weight":"1","pos":40,"context":"1. News from Italy. <mark>Travel<\/mark> to Innsbruck. Has written to the Pope,...","fid":"d111e63"}]},{"docId":"A106","docUri":"A106.html","score":1,"contexts":[{"form":"travel","weight":"1","pos":45,"context":"...been seized by the King of France. Will <mark>travel<\/mark> to Innsbruck within two days. Has sent reports...","fid":"d110e63"}]},{"docId":"A158","docUri":"A158.html","score":1,"contexts":[{"form":"travels","weight":"1","pos":215,"context":"...F about Italy. 18. Don Pedro de Cordova's <mark>travels<\/mark>.","fid":"d161e63"}]},{"docId":"A218","docUri":"A218.html","score":1,"contexts":[{"form":"travel","weight":"1","pos":53,"context":"...Burgundy. Has informed him of F's plans to <mark>travel<\/mark> to Italy and told him it would be good...","fid":"d221e63"}]},{"docId":"A199","docUri":"A199.html","score":1,"contexts":[{"form":"travel","weight":"1","pos":55,"context":"...regarding the Imperial Diet. 2. Unable to personally <mark>travel<\/mark> to Italy at this point. 3. Peasant uprising...","fid":"d202e63"}]},{"docId":"A187","docUri":"A187.html","score":1,"contexts":[{"form":"travel","weight":"1","pos":92,"context":"...the Imperial Diet in Speyer. 6. Willing to <mark>travel<\/mark> to Milan. 7. Milanese salt monopoly. 8....","fid":"d190e63"}]},{"docId":"A005","docUri":"A005.html","score":1,"contexts":[{"form":"travel","weight":"1","pos":63,"context":"...will prove through actions. 3. K will soon <mark>travel<\/mark> to Spain. He requests frequent news. 4....","fid":"d9e64"}]},{"docId":"A103","docUri":"A103.html","score":1,"contexts":[{"form":"travel","weight":"1","pos":66,"context":".... 2. Sending troops to Italy. Wants to <mark>travel<\/mark> to Innsbruck. 3. Has sent one of his...","fid":"d107e63"}]},{"docId":"A223","docUri":"A223.html","score":1,"contexts":[{"form":"travel","weight":"1","pos":49,"context":".... All of Christendom is threatened. 2. Will <mark>travel<\/mark> to Austria in 8 to 10 days. The...","fid":"d226e63"}]},{"docId":"A182","docUri":"A182.html","score":1,"contexts":[{"form":"travels","weight":"1","pos":80,"context":"...with Venice. 4. Council. 5. K's impending <mark>travels<\/mark> to Italy. F shall come to Milan....","fid":"d185e66"}]},{"docId":"A131","docUri":"A131.html","score":1,"contexts":[{"form":"traveled","weight":"1","pos":83,"context":"...battle of Pavia. Reasons for not having personally <mark>traveled<\/mark> to Italy. Found writings from the imperial princes...","fid":"d134e63"}]},{"docId":"A136","docUri":"A136.html","score":1,"contexts":[{"form":"travel","weight":"1","pos":473,"context":"...Bourbon and the Viceroy. 42. F's inability to <mark>travel<\/mark> to Italy.","fid":"d139e63"}]},{"docId":"A145","docUri":"A145.html","score":1,"contexts":[{"form":"travels","weight":"1","pos":121,"context":"...marriage plans regarding the Infanta of Portugal. His <mark>travels<\/mark> to Italy have been delayed. 7. Italian intrigue...","fid":"d148e68"}]},{"docId":"A076","docUri":"A076.html","score":1,"contexts":[{"form":"traveled","weight":"1","pos":1088,"context":"...debt left by Emperor Maximilian I. 52. He has <mark>traveled<\/mark> to Nuremberg on imperial business twice already. He...","fid":"d80e63"}]},{"docId":"A034","docUri":"A034.html","score":1,"contexts":[{"form":"traveled","weight":"1","pos":43,"context":"1. Franz von Sickingen has secretly <mark>traveled<\/mark> to Lorraine. 2. The imperial commissioners are being...","fid":"d38e63"}]}]}