{"stem":"tyrol","instances":[{"docId":"A239","docUri":"A239.html","score":2,"contexts":[{"form":"Tyrol","weight":"1","pos":1128,"context":"...argent, ai fait respondre aulcuns des principaulx de <mark>Tyrol<\/mark>, affin de tant plus promptement pouoir avoir argent...","fid":"d242e183"},{"form":"Tyrol","weight":"1","pos":3672,"context":"...Turcs chiffriert. - n) mieulx —pays de <mark>Tyrol<\/mark> chiffriert. - o) et aussi — donnerai l’occasion...","fid":"d242e898"}]},{"docId":"A021","docUri":"A021.html","score":2,"contexts":[{"form":"Tyrol","weight":"1","pos":441,"context":"...en long temps pourrons lever ni des pays de <mark>Tyrol<\/mark>, Ferrette, Wirtemberg et aultres ung seul patart...","fid":"d25e102"},{"form":"Tyrol","weight":"1","pos":487,"context":"...prince et seigneur naturel des pays et conté de <mark>Tyrol<\/mark>, Ferrette, duchié de Wirtemberg et aultres....","fid":"d25e123"}]},{"docId":"A036","docUri":"A036.html","score":1,"contexts":[{"form":"Tyrol","weight":"1","pos":345,"context":"...d’aulcunes voz lettres au regiment en ceste conté de <mark>Tyrol<\/mark>, lesquelles j’ai veu qu’ilz eussent à bailler aulcuns...","fid":"d40e79"}]},{"docId":"A142","docUri":"A142.html","score":1,"contexts":[{"form":"Tyrol","weight":"1","pos":266,"context":"...m’a rapporté, touchant ce pays et conté de <mark>Tyrol<\/mark>, j’ai, monsr, prolonghé et retardé...","fid":"d145e125"}]},{"docId":"A156","docUri":"A156.html","score":1,"contexts":[{"form":"Tyrol","weight":"1","pos":81,"context":"...passée je tins en Ysbroug à la conté de <mark>Tyrol<\/mark> je fus par les estatz d’illec et aussi des...","fid":"d159e71"}]}]}