{"stem":"zweifelt","instances":[{"docId":"A047","docUri":"A047.html","score":1,"contexts":[{"form":"zweifelte","weight":"1","pos":708,"context":"...tragen. Als Prantner an der Echtheit der Beglaubigung <mark>zweifelte<\/mark> und mit der ersten Post bei F anfragte,...","fid":"d51e375"}]},{"docId":"A189","docUri":"A189.html","score":1,"contexts":[{"form":"zweifelt","weight":"1","pos":53,"context":"...5. P채pstliche Breven 체ber die drohende T체rkengefahr. K <mark>zweifelt<\/mark> an der unmittelbaren Gefahr. 6. Dankt f체r die...","fid":"d192e60"}]}]}